<?xml version="1.0"?>
<APP database="hot" name="Hot" reportpath="/root/baraza/projects/hot/reports/">
	<TREE name="Hot">
		<NODE name="Entries">
			<NODE key="1" name="Bar64"></NODE>
			<NODE key="2" name="Bar65"></NODE>
			<NODE key="3" name="Bar66"></NODE>
			<NODE key="4" name="Bch02"></NODE>
			<NODE key="5" name="Bct95"></NODE>
			<NODE key="6" name="Bfh01"></NODE>
			<NODE key="7" name="Bft99"></NODE>
			<NODE key="8" name="Bkf81"></NODE>
			<NODE key="9" name="Bki63"></NODE>
			<NODE key="10" name="Bkp83"></NODE>
			<NODE key="11" name="Bkp84"></NODE>
			<NODE key="12" name="Bks24"></NODE>
			<NODE key="13" name="Bks30"></NODE>
			<NODE key="14" name="Bks39"></NODE>
			<NODE key="15" name="Bks42"></NODE>
			<NODE key="16" name="Bks45"></NODE>
			<NODE key="17" name="Bks46"></NODE>
			<NODE key="18" name="Bkt06"></NODE>
			<NODE key="19" name="Bmd75"></NODE>
			<NODE key="20" name="Bmd76"></NODE>
			<NODE key="21" name="Bmp70"></NODE>
			<NODE key="22" name="Bmp71"></NODE>
			<NODE key="23" name="Bmp72"></NODE>
			<NODE key="24" name="Bmp73"></NODE>
			<NODE key="25" name="Bmp74"></NODE>
			<NODE key="26" name="Bmp77"></NODE>
			<NODE key="27" name="Bmp78"></NODE>
			<NODE key="28" name="Boh03"></NODE>
			<NODE key="29" name="Bot93"></NODE>
			<NODE key="30" name="Bot94"></NODE>
			<NODE key="31" name="Elements"></NODE>
			<NODE key="32" name="Headers"></NODE>
		</NODE>

		<NODE name="Report">
			<NODE key="101" name="Bar64"></NODE>
			<NODE key="102" name="Bar65"></NODE>
			<NODE key="103" name="Bar66"></NODE>
			<NODE key="104" name="Bch02"></NODE>
			<NODE key="105" name="Bct95"></NODE>
			<NODE key="106" name="Bfh01"></NODE>
			<NODE key="107" name="Bft99"></NODE>
			<NODE key="108" name="Bkf81"></NODE>
			<NODE key="109" name="Bki63"></NODE>
			<NODE key="110" name="Bkp83"></NODE>
			<NODE key="111" name="Bkp84"></NODE>
			<NODE key="112" name="Bks24"></NODE>
			<NODE key="113" name="Bks30"></NODE>
			<NODE key="114" name="Bks39"></NODE>
			<NODE key="115" name="Bks42"></NODE>
			<NODE key="116" name="Bks45"></NODE>
			<NODE key="117" name="Bks46"></NODE>
			<NODE key="118" name="Bkt06"></NODE>
			<NODE key="119" name="Bmd75"></NODE>
			<NODE key="120" name="Bmd76"></NODE>
			<NODE key="121" name="Bmp70"></NODE>
			<NODE key="122" name="Bmp71"></NODE>
			<NODE key="123" name="Bmp72"></NODE>
			<NODE key="124" name="Bmp73"></NODE>
			<NODE key="125" name="Bmp74"></NODE>
			<NODE key="126" name="Bmp77"></NODE>
			<NODE key="127" name="Bmp78"></NODE>
			<NODE key="128" name="Boh03"></NODE>
			<NODE key="129" name="Bot93"></NODE>
			<NODE key="130" name="Bot94"></NODE>
			<NODE key="131" name="Elements"></NODE>
			<NODE key="132" name="Headers"></NODE>
		</NODE>

	</TREE>

	<DESK h="500" key="1" name="Bar64" splitloc="250" splittype="vert" w="585">
		<GRID gridfilter="true" key="1" keyfield="fld0" name="Bar64" pos="top" table="bar64">
			<TEXTFIELD title="Fld0" w="40">fld0</TEXTFIELD>
			<TEXTFIELD title="Fld1" w="40">fld1</TEXTFIELD>
			<TEXTFIELD title="Fld2" w="40">fld2</TEXTFIELD>
			<TEXTFIELD title="Fld3" w="40">fld3</TEXTFIELD>
			<TEXTFIELD title="Fld4" w="40">fld4</TEXTFIELD>
			<TEXTFIELD title="Fld5" w="40">fld5</TEXTFIELD>
			<TEXTFIELD title="Fld6" w="40">fld6</TEXTFIELD>
			<TEXTFIELD title="Fld7" w="40">fld7</TEXTFIELD>
			<TEXTFIELD title="Fld8" w="40">fld8</TEXTFIELD>
			<TEXTFIELD title="Fld9" w="40">fld9</TEXTFIELD>
			<TEXTFIELD title="Fld10" w="40">fld10</TEXTFIELD>
			<TEXTFIELD title="Fld11" w="40">fld11</TEXTFIELD>
			<TEXTFIELD title="Fld12" w="40">fld12</TEXTFIELD>
			<TEXTFIELD title="Fld13" w="40">fld13</TEXTFIELD>
			<TEXTFIELD title="Fld14" w="40">fld14</TEXTFIELD>
			<TEXTFIELD title="Fld15" w="40">fld15</TEXTFIELD>
			<TEXTFIELD title="Fld16" w="40">fld16</TEXTFIELD>
			<TEXTFIELD title="Fld17" w="40">fld17</TEXTFIELD>
			<TEXTFIELD title="Fld18" w="40">fld18</TEXTFIELD>
			<TEXTFIELD title="Fld19" w="40">fld19</TEXTFIELD>
			<TEXTFIELD title="Fld20" w="40">fld20</TEXTFIELD>
			<TEXTFIELD title="Fld21" w="40">fld21</TEXTFIELD>
			<TEXTFIELD title="Fld22" w="40">fld22</TEXTFIELD>
			<TEXTFIELD title="Narrative" w="40">narrative</TEXTFIELD>
		</GRID>

		<FORM autofield="fld0" key="2" linkfield="fld0" linkkey="1" name="Bar64" pos="bottom" table="bar64">
			<TEXTFIELD h="20" title="Fld1" w="150" x="10" y="10">fld1</TEXTFIELD>
			<TEXTFIELD h="20" title="Fld2" w="150" x="290" y="10">fld2</TEXTFIELD>
			<TEXTFIELD h="20" title="Fld3" w="150" x="10" y="30">fld3</TEXTFIELD>
			<TEXTFIELD h="20" title="Fld4" w="150" x="290" y="30">fld4</TEXTFIELD>
			<TEXTFIELD h="20" title="Fld5" w="150" x="10" y="50">fld5</TEXTFIELD>
			<TEXTFIELD h="20" title="Fld6" w="150" x="290" y="50">fld6</TEXTFIELD>
			<TEXTFIELD h="20" title="Fld7" w="150" x="10" y="70">fld7</TEXTFIELD>
			<TEXTFIELD h="20" title="Fld8" w="150" x="290" y="70">fld8</TEXTFIELD>
			<TEXTFIELD h="20" title="Fld9" w="150" x="10" y="90">fld9</TEXTFIELD>
			<TEXTFIELD h="20" title="Fld10" w="150" x="290" y="90">fld10</TEXTFIELD>
			<TEXTFIELD h="20" title="Fld11" w="150" x="10" y="110">fld11</TEXTFIELD>
			<TEXTFIELD h="20" title="Fld12" w="150" x="290" y="110">fld12</TEXTFIELD>
			<TEXTFIELD h="20" title="Fld13" w="150" x="10" y="130">fld13</TEXTFIELD>
			<TEXTFIELD h="20" title="Fld14" w="150" x="290" y="130">fld14</TEXTFIELD>
			<TEXTFIELD h="20" title="Fld15" w="150" x="10" y="150">fld15</TEXTFIELD>
			<TEXTFIELD h="20" title="Fld16" w="150" x="290" y="150">fld16</TEXTFIELD>
			<TEXTFIELD h="20" title="Fld17" w="150" x="10" y="170">fld17</TEXTFIELD>
			<TEXTFIELD h="20" title="Fld18" w="150" x="290" y="170">fld18</TEXTFIELD>
			<TEXTFIELD h="20" title="Fld19" w="150" x="10" y="190">fld19</TEXTFIELD>
			<TEXTFIELD h="20" title="Fld20" w="150" x="290" y="190">fld20</TEXTFIELD>
			<TEXTFIELD h="20" title="Fld21" w="150" x="10" y="210">fld21</TEXTFIELD>
			<TEXTFIELD h="20" title="Fld22" w="150" x="290" y="210">fld22</TEXTFIELD>
			<TEXTFIELD h="20" title="Narrative" w="430" x="10" y="230">narrative</TEXTFIELD>
		</FORM>

	</DESK>

	<DESK h="500" key="2" name="Bar65" splitloc="250" splittype="vert" w="585">
		<GRID gridfilter="true" key="1" keyfield="fld0" name="Bar65" pos="top" table="bar65">
			<TEXTFIELD title="Fld0" w="40">fld0</TEXTFIELD>
			<TEXTFIELD title="Fld1" w="40">fld1</TEXTFIELD>
			<TEXTFIELD title="Fld2" w="40">fld2</TEXTFIELD>
			<TEXTFIELD title="Fld3" w="40">fld3</TEXTFIELD>
			<TEXTFIELD title="Fld4" w="40">fld4</TEXTFIELD>
			<TEXTFIELD title="Fld5" w="40">fld5</TEXTFIELD>
			<TEXTFIELD title="Fld6" w="40">fld6</TEXTFIELD>
			<TEXTFIELD title="Fld7" w="40">fld7</TEXTFIELD>
			<TEXTFIELD title="Fld8" w="40">fld8</TEXTFIELD>
			<TEXTFIELD title="Fld9" w="40">fld9</TEXTFIELD>
			<TEXTFIELD title="Narrative" w="40">narrative</TEXTFIELD>
		</GRID>

		<FORM autofield="fld0" key="2" linkfield="fld0" linkkey="1" name="Bar65" pos="bottom" table="bar65">
			<TEXTFIELD h="20" title="Fld1" w="150" x="10" y="10">fld1</TEXTFIELD>
			<TEXTFIELD h="20" title="Fld2" w="150" x="290" y="10">fld2</TEXTFIELD>
			<TEXTFIELD h="20" title="Fld3" w="150" x="10" y="30">fld3</TEXTFIELD>
			<TEXTFIELD h="20" title="Fld4" w="150" x="290" y="30">fld4</TEXTFIELD>
			<TEXTFIELD h="20" title="Fld5" w="150" x="10" y="50">fld5</TEXTFIELD>
			<TEXTFIELD h="20" title="Fld6" w="150" x="290" y="50">fld6</TEXTFIELD>
			<TEXTFIELD h="20" title="Fld7" w="150" x="10" y="70">fld7</TEXTFIELD>
			<TEXTFIELD h="20" title="Fld8" w="150" x="290" y="70">fld8</TEXTFIELD>
			<TEXTFIELD h="20" title="Fld9" w="150" x="10" y="90">fld9</TEXTFIELD>
			<TEXTFIELD h="20" title="Narrative" w="430" x="10" y="110">narrative</TEXTFIELD>
		</FORM>

	</DESK>

	<DESK h="500" key="3" name="Bar66" splitloc="250" splittype="vert" w="585">
		<GRID gridfilter="true" key="1" keyfield="fld0" name="Bar66" pos="top" table="bar66">
			<TEXTFIELD title="Fld0" w="40">fld0</TEXTFIELD>
			<TEXTFIELD title="Fld1" w="40">fld1</TEXTFIELD>
			<TEXTFIELD title="Fld2" w="40">fld2</TEXTFIELD>
			<TEXTFIELD title="Fld3" w="40">fld3</TEXTFIELD>
			<TEXTFIELD title="Fld4" w="40">fld4</TEXTFIELD>
			<TEXTFIELD title="Fld5" w="40">fld5</TEXTFIELD>
			<TEXTFIELD title="Fld6" w="40">fld6</TEXTFIELD>
			<TEXTFIELD title="Fld7" w="40">fld7</TEXTFIELD>
			<TEXTFIELD title="Fld8" w="40">fld8</TEXTFIELD>
			<TEXTFIELD title="Fld9" w="40">fld9</TEXTFIELD>
			<TEXTFIELD title="Fld10" w="40">fld10</TEXTFIELD>
			<TEXTFIELD title="Narrative" w="40">narrative</TEXTFIELD>
		</GRID>

		<FORM autofield="fld0" key="2" linkfield="fld0" linkkey="1" name="Bar66" pos="bottom" table="bar66">
			<TEXTFIELD h="20" title="Fld1" w="150" x="10" y="10">fld1</TEXTFIELD>
			<TEXTFIELD h="20" title="Fld2" w="150" x="290" y="10">fld2</TEXTFIELD>
			<TEXTFIELD h="20" title="Fld3" w="150" x="10" y="30">fld3</TEXTFIELD>
			<TEXTFIELD h="20" title="Fld4" w="150" x="290" y="30">fld4</TEXTFIELD>
			<TEXTFIELD h="20" title="Fld5" w="150" x="10" y="50">fld5</TEXTFIELD>
			<TEXTFIELD h="20" title="Fld6" w="150" x="290" y="50">fld6</TEXTFIELD>
			<TEXTFIELD h="20" title="Fld7" w="150" x="10" y="70">fld7</TEXTFIELD>
			<TEXTFIELD h="20" title="Fld8" w="150" x="290" y="70">fld8</TEXTFIELD>
			<TEXTFIELD h="20" title="Fld9" w="150" x="10" y="90">fld9</TEXTFIELD>
			<TEXTFIELD h="20" title="Fld10" w="150" x="290" y="90">fld10</TEXTFIELD>
			<TEXTFIELD h="20" title="Narrative" w="430" x="10" y="110">narrative</TEXTFIELD>
		</FORM>

	</DESK>

	<DESK h="500" key="4" name="Bch02" splitloc="250" splittype="vert" w="585">
		<GRID gridfilter="true" key="1" keyfield="fld0" name="Bch02" pos="top" table="bch02">
			<TEXTFIELD title="Fld0" w="40">fld0</TEXTFIELD>
			<TEXTFIELD title="Fld1" w="40">fld1</TEXTFIELD>
			<TEXTFIELD title="Fld2" w="40">fld2</TEXTFIELD>
			<TEXTFIELD title="Fld3" w="40">fld3</TEXTFIELD>
			<TEXTFIELD title="Fld4" w="40">fld4</TEXTFIELD>
			<TEXTFIELD title="Fld5" w="40">fld5</TEXTFIELD>
			<TEXTFIELD title="Fld6" w="40">fld6</TEXTFIELD>
			<TEXTFIELD title="Fld7" w="40">fld7</TEXTFIELD>
			<TEXTFIELD title="Fld8" w="40">fld8</TEXTFIELD>
			<TEXTFIELD title="Fld9" w="40">fld9</TEXTFIELD>
			<TEXTFIELD title="Narrative" w="40">narrative</TEXTFIELD>
		</GRID>

		<FORM autofield="fld0" key="2" linkfield="fld0" linkkey="1" name="Bch02" pos="bottom" table="bch02">
			<TEXTFIELD h="20" title="Fld1" w="150" x="10" y="10">fld1</TEXTFIELD>
			<TEXTFIELD h="20" title="Fld2" w="150" x="290" y="10">fld2</TEXTFIELD>
			<TEXTFIELD h="20" title="Fld3" w="150" x="10" y="30">fld3</TEXTFIELD>
			<TEXTFIELD h="20" title="Fld4" w="150" x="290" y="30">fld4</TEXTFIELD>
			<TEXTFIELD h="20" title="Fld5" w="150" x="10" y="50">fld5</TEXTFIELD>
			<TEXTFIELD h="20" title="Fld6" w="150" x="290" y="50">fld6</TEXTFIELD>
			<TEXTFIELD h="20" title="Fld7" w="150" x="10" y="70">fld7</TEXTFIELD>
			<TEXTFIELD h="20" title="Fld8" w="150" x="290" y="70">fld8</TEXTFIELD>
			<TEXTFIELD h="20" title="Fld9" w="150" x="10" y="90">fld9</TEXTFIELD>
			<TEXTFIELD h="20" title="Narrative" w="430" x="10" y="110">narrative</TEXTFIELD>
		</FORM>

	</DESK>

	<DESK h="500" key="5" name="Bct95" splitloc="250" splittype="vert" w="585">
		<GRID gridfilter="true" key="1" keyfield="fld0" name="Bct95" pos="top" table="bct95">
			<TEXTFIELD title="Fld0" w="40">fld0</TEXTFIELD>
			<TEXTFIELD title="Fld1" w="40">fld1</TEXTFIELD>
			<TEXTFIELD title="Fld2" w="40">fld2</TEXTFIELD>
			<TEXTFIELD title="Fld3" w="40">fld3</TEXTFIELD>
			<TEXTFIELD title="Fld4" w="40">fld4</TEXTFIELD>
			<TEXTFIELD title="Fld5" w="40">fld5</TEXTFIELD>
			<TEXTFIELD title="Fld6" w="40">fld6</TEXTFIELD>
			<TEXTFIELD title="Fld7" w="40">fld7</TEXTFIELD>
			<TEXTFIELD title="Fld8" w="40">fld8</TEXTFIELD>
			<TEXTFIELD title="Fld9" w="40">fld9</TEXTFIELD>
			<TEXTFIELD title="Fld10" w="40">fld10</TEXTFIELD>
			<TEXTFIELD title="Fld11" w="40">fld11</TEXTFIELD>
			<TEXTFIELD title="Fld12" w="40">fld12</TEXTFIELD>
			<TEXTFIELD title="Fld13" w="40">fld13</TEXTFIELD>
			<TEXTFIELD title="Fld14" w="40">fld14</TEXTFIELD>
			<TEXTFIELD title="Fld15" w="40">fld15</TEXTFIELD>
			<TEXTFIELD title="Fld16" w="40">fld16</TEXTFIELD>
			<TEXTFIELD title="Narrative" w="40">narrative</TEXTFIELD>
		</GRID>

		<FORM autofield="fld0" key="2" linkfield="fld0" linkkey="1" name="Bct95" pos="bottom" table="bct95">
			<TEXTFIELD h="20" title="Fld1" w="150" x="10" y="10">fld1</TEXTFIELD>
			<TEXTFIELD h="20" title="Fld2" w="150" x="290" y="10">fld2</TEXTFIELD>
			<TEXTFIELD h="20" title="Fld3" w="150" x="10" y="30">fld3</TEXTFIELD>
			<TEXTFIELD h="20" title="Fld4" w="150" x="290" y="30">fld4</TEXTFIELD>
			<TEXTFIELD h="20" title="Fld5" w="150" x="10" y="50">fld5</TEXTFIELD>
			<TEXTFIELD h="20" title="Fld6" w="150" x="290" y="50">fld6</TEXTFIELD>
			<TEXTFIELD h="20" title="Fld7" w="150" x="10" y="70">fld7</TEXTFIELD>
			<TEXTFIELD h="20" title="Fld8" w="150" x="290" y="70">fld8</TEXTFIELD>
			<TEXTFIELD h="20" title="Fld9" w="150" x="10" y="90">fld9</TEXTFIELD>
			<TEXTFIELD h="20" title="Fld10" w="150" x="290" y="90">fld10</TEXTFIELD>
			<TEXTFIELD h="20" title="Fld11" w="150" x="10" y="110">fld11</TEXTFIELD>
			<TEXTFIELD h="20" title="Fld12" w="150" x="290" y="110">fld12</TEXTFIELD>
			<TEXTFIELD h="20" title="Fld13" w="150" x="10" y="130">fld13</TEXTFIELD>
			<TEXTFIELD h="20" title="Fld14" w="150" x="290" y="130">fld14</TEXTFIELD>
			<TEXTFIELD h="20" title="Fld15" w="150" x="10" y="150">fld15</TEXTFIELD>
			<TEXTFIELD h="20" title="Fld16" w="150" x="290" y="150">fld16</TEXTFIELD>
			<TEXTFIELD h="20" title="Narrative" w="430" x="10" y="170">narrative</TEXTFIELD>
		</FORM>

	</DESK>

	<DESK h="500" key="6" name="Bfh01" splitloc="250" splittype="vert" w="585">
		<GRID gridfilter="true" key="1" keyfield="fld0" name="Bfh01" pos="top" table="bfh01">
			<TEXTFIELD title="Fld0" w="40">fld0</TEXTFIELD>
			<TEXTFIELD title="Fld1" w="40">fld1</TEXTFIELD>
			<TEXTFIELD title="Fld2" w="40">fld2</TEXTFIELD>
			<TEXTFIELD title="Fld3" w="40">fld3</TEXTFIELD>
			<TEXTFIELD title="Fld4" w="40">fld4</TEXTFIELD>
			<TEXTFIELD title="Fld5" w="40">fld5</TEXTFIELD>
			<TEXTFIELD title="Fld6" w="40">fld6</TEXTFIELD>
			<TEXTFIELD title="Fld7" w="40">fld7</TEXTFIELD>
			<TEXTFIELD title="Fld8" w="40">fld8</TEXTFIELD>
			<TEXTFIELD title="Fld9" w="40">fld9</TEXTFIELD>
			<TEXTFIELD title="Fld10" w="40">fld10</TEXTFIELD>
			<TEXTFIELD title="Fld11" w="40">fld11</TEXTFIELD>
			<TEXTFIELD title="Fld12" w="40">fld12</TEXTFIELD>
			<TEXTFIELD title="Narrative" w="40">narrative</TEXTFIELD>
		</GRID>

		<FORM autofield="fld0" key="2" linkfield="fld0" linkkey="1" name="Bfh01" pos="bottom" table="bfh01">
			<TEXTFIELD h="20" title="Fld1" w="150" x="10" y="10">fld1</TEXTFIELD>
			<TEXTFIELD h="20" title="Fld2" w="150" x="290" y="10">fld2</TEXTFIELD>
			<TEXTFIELD h="20" title="Fld3" w="150" x="10" y="30">fld3</TEXTFIELD>
			<TEXTFIELD h="20" title="Fld4" w="150" x="290" y="30">fld4</TEXTFIELD>
			<TEXTFIELD h="20" title="Fld5" w="150" x="10" y="50">fld5</TEXTFIELD>
			<TEXTFIELD h="20" title="Fld6" w="150" x="290" y="50">fld6</TEXTFIELD>
			<TEXTFIELD h="20" title="Fld7" w="150" x="10" y="70">fld7</TEXTFIELD>
			<TEXTFIELD h="20" title="Fld8" w="150" x="290" y="70">fld8</TEXTFIELD>
			<TEXTFIELD h="20" title="Fld9" w="150" x="10" y="90">fld9</TEXTFIELD>
			<TEXTFIELD h="20" title="Fld10" w="150" x="290" y="90">fld10</TEXTFIELD>
			<TEXTFIELD h="20" title="Fld11" w="150" x="10" y="110">fld11</TEXTFIELD>
			<TEXTFIELD h="20" title="Fld12" w="150" x="290" y="110">fld12</TEXTFIELD>
			<TEXTFIELD h="20" title="Narrative" w="430" x="10" y="130">narrative</TEXTFIELD>
		</FORM>

	</DESK>

	<DESK h="500" key="7" name="Bft99" splitloc="250" splittype="vert" w="585">
		<GRID gridfilter="true" key="1" keyfield="fld0" name="Bft99" pos="top" table="bft99">
			<TEXTFIELD title="Fld0" w="40">fld0</TEXTFIELD>
			<TEXTFIELD title="Fld1" w="40">fld1</TEXTFIELD>
			<TEXTFIELD title="Fld2" w="40">fld2</TEXTFIELD>
			<TEXTFIELD title="Fld3" w="40">fld3</TEXTFIELD>
			<TEXTFIELD title="Fld4" w="40">fld4</TEXTFIELD>
			<TEXTFIELD title="Fld5" w="40">fld5</TEXTFIELD>
			<TEXTFIELD title="Fld6" w="40">fld6</TEXTFIELD>
			<TEXTFIELD title="Fld7" w="40">fld7</TEXTFIELD>
			<TEXTFIELD title="Fld8" w="40">fld8</TEXTFIELD>
			<TEXTFIELD title="Fld9" w="40">fld9</TEXTFIELD>
			<TEXTFIELD title="Fld10" w="40">fld10</TEXTFIELD>
			<TEXTFIELD title="Fld11" w="40">fld11</TEXTFIELD>
			<TEXTFIELD title="Fld12" w="40">fld12</TEXTFIELD>
			<TEXTFIELD title="Fld13" w="40">fld13</TEXTFIELD>
			<TEXTFIELD title="Fld14" w="40">fld14</TEXTFIELD>
			<TEXTFIELD title="Fld15" w="40">fld15</TEXTFIELD>
			<TEXTFIELD title="Narrative" w="40">narrative</TEXTFIELD>
		</GRID>

		<FORM autofield="fld0" key="2" linkfield="fld0" linkkey="1" name="Bft99" pos="bottom" table="bft99">
			<TEXTFIELD h="20" title="Fld1" w="150" x="10" y="10">fld1</TEXTFIELD>
			<TEXTFIELD h="20" title="Fld2" w="150" x="290" y="10">fld2</TEXTFIELD>
			<TEXTFIELD h="20" title="Fld3" w="150" x="10" y="30">fld3</TEXTFIELD>
			<TEXTFIELD h="20" title="Fld4" w="150" x="290" y="30">fld4</TEXTFIELD>
			<TEXTFIELD h="20" title="Fld5" w="150" x="10" y="50">fld5</TEXTFIELD>
			<TEXTFIELD h="20" title="Fld6" w="150" x="290" y="50">fld6</TEXTFIELD>
			<TEXTFIELD h="20" title="Fld7" w="150" x="10" y="70">fld7</TEXTFIELD>
			<TEXTFIELD h="20" title="Fld8" w="150" x="290" y="70">fld8</TEXTFIELD>
			<TEXTFIELD h="20" title="Fld9" w="150" x="10" y="90">fld9</TEXTFIELD>
			<TEXTFIELD h="20" title="Fld10" w="150" x="290" y="90">fld10</TEXTFIELD>
			<TEXTFIELD h="20" title="Fld11" w="150" x="10" y="110">fld11</TEXTFIELD>
			<TEXTFIELD h="20" title="Fld12" w="150" x="290" y="110">fld12</TEXTFIELD>
			<TEXTFIELD h="20" title="Fld13" w="150" x="10" y="130">fld13</TEXTFIELD>
			<TEXTFIELD h="20" title="Fld14" w="150" x="290" y="130">fld14</TEXTFIELD>
			<TEXTFIELD h="20" title="Fld15" w="150" x="10" y="150">fld15</TEXTFIELD>
			<TEXTFIELD h="20" title="Narrative" w="430" x="10" y="170">narrative</TEXTFIELD>
		</FORM>

	</DESK>

	<DESK h="500" key="8" name="Bkf81" splitloc="250" splittype="vert" w="585">
		<GRID gridfilter="true" key="1" keyfield="fld0" name="Bkf81" pos="top" table="bkf81">
			<TEXTFIELD title="Fld0" w="40">fld0</TEXTFIELD>
			<TEXTFIELD title="Fld1" w="40">fld1</TEXTFIELD>
			<TEXTFIELD title="Fld2" w="40">fld2</TEXTFIELD>
			<TEXTFIELD title="Fld3" w="40">fld3</TEXTFIELD>
			<TEXTFIELD title="Fld4" w="40">fld4</TEXTFIELD>
			<TEXTFIELD title="Fld5" w="40">fld5</TEXTFIELD>
			<TEXTFIELD title="Fld6" w="40">fld6</TEXTFIELD>
			<TEXTFIELD title="Fld7" w="40">fld7</TEXTFIELD>
			<TEXTFIELD title="Fld8" w="40">fld8</TEXTFIELD>
			<TEXTFIELD title="Fld9" w="40">fld9</TEXTFIELD>
			<TEXTFIELD title="Fld10" w="40">fld10</TEXTFIELD>
			<TEXTFIELD title="Fld11" w="40">fld11</TEXTFIELD>
			<TEXTFIELD title="Narrative" w="40">narrative</TEXTFIELD>
		</GRID>

		<FORM autofield="fld0" key="2" linkfield="fld0" linkkey="1" name="Bkf81" pos="bottom" table="bkf81">
			<TEXTFIELD h="20" title="Fld1" w="150" x="10" y="10">fld1</TEXTFIELD>
			<TEXTFIELD h="20" title="Fld2" w="150" x="290" y="10">fld2</TEXTFIELD>
			<TEXTFIELD h="20" title="Fld3" w="150" x="10" y="30">fld3</TEXTFIELD>
			<TEXTFIELD h="20" title="Fld4" w="150" x="290" y="30">fld4</TEXTFIELD>
			<TEXTFIELD h="20" title="Fld5" w="150" x="10" y="50">fld5</TEXTFIELD>
			<TEXTFIELD h="20" title="Fld6" w="150" x="290" y="50">fld6</TEXTFIELD>
			<TEXTFIELD h="20" title="Fld7" w="150" x="10" y="70">fld7</TEXTFIELD>
			<TEXTFIELD h="20" title="Fld8" w="150" x="290" y="70">fld8</TEXTFIELD>
			<TEXTFIELD h="20" title="Fld9" w="150" x="10" y="90">fld9</TEXTFIELD>
			<TEXTFIELD h="20" title="Fld10" w="150" x="290" y="90">fld10</TEXTFIELD>
			<TEXTFIELD h="20" title="Fld11" w="150" x="10" y="110">fld11</TEXTFIELD>
			<TEXTFIELD h="20" title="Narrative" w="430" x="10" y="130">narrative</TEXTFIELD>
		</FORM>

	</DESK>

	<DESK h="500" key="9" name="Bki63" splitloc="250" splittype="vert" w="585">
		<GRID gridfilter="true" key="1" keyfield="fld0" name="Bki63" pos="top" table="bki63">
			<TEXTFIELD title="Fld0" w="40">fld0</TEXTFIELD>
			<TEXTFIELD title="Fld1" w="40">fld1</TEXTFIELD>
			<TEXTFIELD title="Fld2" w="40">fld2</TEXTFIELD>
			<TEXTFIELD title="Fld3" w="40">fld3</TEXTFIELD>
			<TEXTFIELD title="Fld4" w="40">fld4</TEXTFIELD>
			<TEXTFIELD title="Fld5" w="40">fld5</TEXTFIELD>
			<TEXTFIELD title="Fld6" w="40">fld6</TEXTFIELD>
			<TEXTFIELD title="Fld7" w="40">fld7</TEXTFIELD>
			<TEXTFIELD title="Fld8" w="40">fld8</TEXTFIELD>
			<TEXTFIELD title="Fld9" w="40">fld9</TEXTFIELD>
			<TEXTFIELD title="Fld10" w="40">fld10</TEXTFIELD>
			<TEXTFIELD title="Fld11" w="40">fld11</TEXTFIELD>
			<TEXTFIELD title="Fld12" w="40">fld12</TEXTFIELD>
			<TEXTFIELD title="Fld13" w="40">fld13</TEXTFIELD>
			<TEXTFIELD title="Fld14" w="40">fld14</TEXTFIELD>
			<TEXTFIELD title="Fld15" w="40">fld15</TEXTFIELD>
			<TEXTFIELD title="Fld16" w="40">fld16</TEXTFIELD>
			<TEXTFIELD title="Fld17" w="40">fld17</TEXTFIELD>
			<TEXTFIELD title="Fld18" w="40">fld18</TEXTFIELD>
			<TEXTFIELD title="Fld19" w="40">fld19</TEXTFIELD>
			<TEXTFIELD title="Fld20" w="40">fld20</TEXTFIELD>
			<TEXTFIELD title="Fld21" w="40">fld21</TEXTFIELD>
			<TEXTFIELD title="Fld22" w="40">fld22</TEXTFIELD>
			<TEXTFIELD title="Fld23" w="40">fld23</TEXTFIELD>
			<TEXTFIELD title="Fld24" w="40">fld24</TEXTFIELD>
			<TEXTFIELD title="Fld25" w="40">fld25</TEXTFIELD>
			<TEXTFIELD title="Fld26" w="40">fld26</TEXTFIELD>
			<TEXTFIELD title="Fld27" w="40">fld27</TEXTFIELD>
			<TEXTFIELD title="Fld28" w="40">fld28</TEXTFIELD>
			<TEXTFIELD title="Narrative" w="40">narrative</TEXTFIELD>
		</GRID>

		<FORM autofield="fld0" key="2" linkfield="fld0" linkkey="1" name="Bki63" pos="bottom" table="bki63">
			<TEXTFIELD h="20" title="Fld1" w="150" x="10" y="10">fld1</TEXTFIELD>
			<TEXTFIELD h="20" title="Fld2" w="150" x="290" y="10">fld2</TEXTFIELD>
			<TEXTFIELD h="20" title="Fld3" w="150" x="10" y="30">fld3</TEXTFIELD>
			<TEXTFIELD h="20" title="Fld4" w="150" x="290" y="30">fld4</TEXTFIELD>
			<TEXTFIELD h="20" title="Fld5" w="150" x="10" y="50">fld5</TEXTFIELD>
			<TEXTFIELD h="20" title="Fld6" w="150" x="290" y="50">fld6</TEXTFIELD>
			<TEXTFIELD h="20" title="Fld7" w="150" x="10" y="70">fld7</TEXTFIELD>
			<TEXTFIELD h="20" title="Fld8" w="150" x="290" y="70">fld8</TEXTFIELD>
			<TEXTFIELD h="20" title="Fld9" w="150" x="10" y="90">fld9</TEXTFIELD>
			<TEXTFIELD h="20" title="Fld10" w="150" x="290" y="90">fld10</TEXTFIELD>
			<TEXTFIELD h="20" title="Fld11" w="150" x="10" y="110">fld11</TEXTFIELD>
			<TEXTFIELD h="20" title="Fld12" w="150" x="290" y="110">fld12</TEXTFIELD>
			<TEXTFIELD h="20" title="Fld13" w="150" x="10" y="130">fld13</TEXTFIELD>
			<TEXTFIELD h="20" title="Fld14" w="150" x="290" y="130">fld14</TEXTFIELD>
			<TEXTFIELD h="20" title="Fld15" w="150" x="10" y="150">fld15</TEXTFIELD>
			<TEXTFIELD h="20" title="Fld16" w="150" x="290" y="150">fld16</TEXTFIELD>
			<TEXTFIELD h="20" title="Fld17" w="150" x="10" y="170">fld17</TEXTFIELD>
			<TEXTFIELD h="20" title="Fld18" w="150" x="290" y="170">fld18</TEXTFIELD>
			<TEXTFIELD h="20" title="Fld19" w="150" x="10" y="190">fld19</TEXTFIELD>
			<TEXTFIELD h="20" title="Fld20" w="150" x="290" y="190">fld20</TEXTFIELD>
			<TEXTFIELD h="20" title="Fld21" w="150" x="10" y="210">fld21</TEXTFIELD>
			<TEXTFIELD h="20" title="Fld22" w="150" x="290" y="210">fld22</TEXTFIELD>
			<TEXTFIELD h="20" title="Fld23" w="150" x="10" y="230">fld23</TEXTFIELD>
			<TEXTFIELD h="20" title="Fld24" w="150" x="290" y="230">fld24</TEXTFIELD>
			<TEXTFIELD h="20" title="Fld25" w="150" x="10" y="250">fld25</TEXTFIELD>
			<TEXTFIELD h="20" title="Fld26" w="150" x="290" y="250">fld26</TEXTFIELD>
			<TEXTFIELD h="20" title="Fld27" w="150" x="10" y="270">fld27</TEXTFIELD>
			<TEXTFIELD h="20" title="Fld28" w="150" x="290" y="270">fld28</TEXTFIELD>
			<TEXTFIELD h="20" title="Narrative" w="430" x="10" y="290">narrative</TEXTFIELD>
		</FORM>

	</DESK>

	<DESK h="500" key="10" name="Bkp83" splitloc="250" splittype="vert" w="585">
		<GRID gridfilter="true" key="1" keyfield="fld0" name="Bkp83" pos="top" table="bkp83">
			<TEXTFIELD title="Fld0" w="40">fld0</TEXTFIELD>
			<TEXTFIELD title="Fld1" w="40">fld1</TEXTFIELD>
			<TEXTFIELD title="Fld2" w="40">fld2</TEXTFIELD>
			<TEXTFIELD title="Fld3" w="40">fld3</TEXTFIELD>
			<TEXTFIELD title="Fld4" w="40">fld4</TEXTFIELD>
			<TEXTFIELD title="Fld5" w="40">fld5</TEXTFIELD>
			<TEXTFIELD title="Fld6" w="40">fld6</TEXTFIELD>
			<TEXTFIELD title="Fld7" w="40">fld7</TEXTFIELD>
			<TEXTFIELD title="Narrative" w="40">narrative</TEXTFIELD>
		</GRID>

		<FORM autofield="fld0" key="2" linkfield="fld0" linkkey="1" name="Bkp83" pos="bottom" table="bkp83">
			<TEXTFIELD h="20" title="Fld1" w="150" x="10" y="10">fld1</TEXTFIELD>
			<TEXTFIELD h="20" title="Fld2" w="150" x="290" y="10">fld2</TEXTFIELD>
			<TEXTFIELD h="20" title="Fld3" w="150" x="10" y="30">fld3</TEXTFIELD>
			<TEXTFIELD h="20" title="Fld4" w="150" x="290" y="30">fld4</TEXTFIELD>
			<TEXTFIELD h="20" title="Fld5" w="150" x="10" y="50">fld5</TEXTFIELD>
			<TEXTFIELD h="20" title="Fld6" w="150" x="290" y="50">fld6</TEXTFIELD>
			<TEXTFIELD h="20" title="Fld7" w="150" x="10" y="70">fld7</TEXTFIELD>
			<TEXTFIELD h="20" title="Narrative" w="430" x="10" y="90">narrative</TEXTFIELD>
		</FORM>

	</DESK>

	<DESK h="500" key="11" name="Bkp84" splitloc="250" splittype="vert" w="585">
		<GRID gridfilter="true" key="1" keyfield="fld0" name="Bkp84" pos="top" table="bkp84">
			<TEXTFIELD title="Fld0" w="40">fld0</TEXTFIELD>
			<TEXTFIELD title="Fld1" w="40">fld1</TEXTFIELD>
			<TEXTFIELD title="Fld2" w="40">fld2</TEXTFIELD>
			<TEXTFIELD title="Fld3" w="40">fld3</TEXTFIELD>
			<TEXTFIELD title="Fld4" w="40">fld4</TEXTFIELD>
			<TEXTFIELD title="Fld5" w="40">fld5</TEXTFIELD>
			<TEXTFIELD title="Fld6" w="40">fld6</TEXTFIELD>
			<TEXTFIELD title="Fld7" w="40">fld7</TEXTFIELD>
			<TEXTFIELD title="Fld8" w="40">fld8</TEXTFIELD>
			<TEXTFIELD title="Fld9" w="40">fld9</TEXTFIELD>
			<TEXTFIELD title="Fld10" w="40">fld10</TEXTFIELD>
			<TEXTFIELD title="Fld11" w="40">fld11</TEXTFIELD>
			<TEXTFIELD title="Fld12" w="40">fld12</TEXTFIELD>
			<TEXTFIELD title="Fld13" w="40">fld13</TEXTFIELD>
			<TEXTFIELD title="Fld14" w="40">fld14</TEXTFIELD>
			<TEXTFIELD title="Fld15" w="40">fld15</TEXTFIELD>
			<TEXTFIELD title="Fld16" w="40">fld16</TEXTFIELD>
			<TEXTFIELD title="Fld17" w="40">fld17</TEXTFIELD>
			<TEXTFIELD title="Fld18" w="40">fld18</TEXTFIELD>
			<TEXTFIELD title="Fld19" w="40">fld19</TEXTFIELD>
			<TEXTFIELD title="Fld20" w="40">fld20</TEXTFIELD>
			<TEXTFIELD title="Narrative" w="40">narrative</TEXTFIELD>
		</GRID>

		<FORM autofield="fld0" key="2" linkfield="fld0" linkkey="1" name="Bkp84" pos="bottom" table="bkp84">
			<TEXTFIELD h="20" title="Fld1" w="150" x="10" y="10">fld1</TEXTFIELD>
			<TEXTFIELD h="20" title="Fld2" w="150" x="290" y="10">fld2</TEXTFIELD>
			<TEXTFIELD h="20" title="Fld3" w="150" x="10" y="30">fld3</TEXTFIELD>
			<TEXTFIELD h="20" title="Fld4" w="150" x="290" y="30">fld4</TEXTFIELD>
			<TEXTFIELD h="20" title="Fld5" w="150" x="10" y="50">fld5</TEXTFIELD>
			<TEXTFIELD h="20" title="Fld6" w="150" x="290" y="50">fld6</TEXTFIELD>
			<TEXTFIELD h="20" title="Fld7" w="150" x="10" y="70">fld7</TEXTFIELD>
			<TEXTFIELD h="20" title="Fld8" w="150" x="290" y="70">fld8</TEXTFIELD>
			<TEXTFIELD h="20" title="Fld9" w="150" x="10" y="90">fld9</TEXTFIELD>
			<TEXTFIELD h="20" title="Fld10" w="150" x="290" y="90">fld10</TEXTFIELD>
			<TEXTFIELD h="20" title="Fld11" w="150" x="10" y="110">fld11</TEXTFIELD>
			<TEXTFIELD h="20" title="Fld12" w="150" x="290" y="110">fld12</TEXTFIELD>
			<TEXTFIELD h="20" title="Fld13" w="150" x="10" y="130">fld13</TEXTFIELD>
			<TEXTFIELD h="20" title="Fld14" w="150" x="290" y="130">fld14</TEXTFIELD>
			<TEXTFIELD h="20" title="Fld15" w="150" x="10" y="150">fld15</TEXTFIELD>
			<TEXTFIELD h="20" title="Fld16" w="150" x="290" y="150">fld16</TEXTFIELD>
			<TEXTFIELD h="20" title="Fld17" w="150" x="10" y="170">fld17</TEXTFIELD>
			<TEXTFIELD h="20" title="Fld18" w="150" x="290" y="170">fld18</TEXTFIELD>
			<TEXTFIELD h="20" title="Fld19" w="150" x="10" y="190">fld19</TEXTFIELD>
			<TEXTFIELD h="20" title="Fld20" w="150" x="290" y="190">fld20</TEXTFIELD>
			<TEXTFIELD h="20" title="Narrative" w="430" x="10" y="210">narrative</TEXTFIELD>
		</FORM>

	</DESK>

	<DESK h="500" key="12" name="Bks24" splitloc="250" splittype="vert" w="585">
		<GRID gridfilter="true" key="1" keyfield="fld0" name="Bks24" pos="top" table="bks24">
			<TEXTFIELD title="Fld0" w="40">fld0</TEXTFIELD>
			<TEXTFIELD title="Fld1" w="40">fld1</TEXTFIELD>
			<TEXTFIELD title="Fld2" w="40">fld2</TEXTFIELD>
			<TEXTFIELD title="Fld3" w="40">fld3</TEXTFIELD>
			<TEXTFIELD title="Fld4" w="40">fld4</TEXTFIELD>
			<TEXTFIELD title="Fld5" w="40">fld5</TEXTFIELD>
			<TEXTFIELD title="Fld6" w="40">fld6</TEXTFIELD>
			<TEXTFIELD title="Fld7" w="40">fld7</TEXTFIELD>
			<TEXTFIELD title="Fld8" w="40">fld8</TEXTFIELD>
			<TEXTFIELD title="Fld9" w="40">fld9</TEXTFIELD>
			<TEXTFIELD title="Fld10" w="40">fld10</TEXTFIELD>
			<TEXTFIELD title="Fld11" w="40">fld11</TEXTFIELD>
			<TEXTFIELD title="Fld12" w="40">fld12</TEXTFIELD>
			<TEXTFIELD title="Fld13" w="40">fld13</TEXTFIELD>
			<TEXTFIELD title="Fld14" w="40">fld14</TEXTFIELD>
			<TEXTFIELD title="Fld15" w="40">fld15</TEXTFIELD>
			<TEXTFIELD title="Fld16" w="40">fld16</TEXTFIELD>
			<TEXTFIELD title="Fld17" w="40">fld17</TEXTFIELD>
			<TEXTFIELD title="Fld18" w="40">fld18</TEXTFIELD>
			<TEXTFIELD title="Fld19" w="40">fld19</TEXTFIELD>
			<TEXTFIELD title="Narrative" w="40">narrative</TEXTFIELD>
		</GRID>

		<FORM autofield="fld0" key="2" linkfield="fld0" linkkey="1" name="Bks24" pos="bottom" table="bks24">
			<TEXTFIELD h="20" title="Fld1" w="150" x="10" y="10">fld1</TEXTFIELD>
			<TEXTFIELD h="20" title="Fld2" w="150" x="290" y="10">fld2</TEXTFIELD>
			<TEXTFIELD h="20" title="Fld3" w="150" x="10" y="30">fld3</TEXTFIELD>
			<TEXTFIELD h="20" title="Fld4" w="150" x="290" y="30">fld4</TEXTFIELD>
			<TEXTFIELD h="20" title="Fld5" w="150" x="10" y="50">fld5</TEXTFIELD>
			<TEXTFIELD h="20" title="Fld6" w="150" x="290" y="50">fld6</TEXTFIELD>
			<TEXTFIELD h="20" title="Fld7" w="150" x="10" y="70">fld7</TEXTFIELD>
			<TEXTFIELD h="20" title="Fld8" w="150" x="290" y="70">fld8</TEXTFIELD>
			<TEXTFIELD h="20" title="Fld9" w="150" x="10" y="90">fld9</TEXTFIELD>
			<TEXTFIELD h="20" title="Fld10" w="150" x="290" y="90">fld10</TEXTFIELD>
			<TEXTFIELD h="20" title="Fld11" w="150" x="10" y="110">fld11</TEXTFIELD>
			<TEXTFIELD h="20" title="Fld12" w="150" x="290" y="110">fld12</TEXTFIELD>
			<TEXTFIELD h="20" title="Fld13" w="150" x="10" y="130">fld13</TEXTFIELD>
			<TEXTFIELD h="20" title="Fld14" w="150" x="290" y="130">fld14</TEXTFIELD>
			<TEXTFIELD h="20" title="Fld15" w="150" x="10" y="150">fld15</TEXTFIELD>
			<TEXTFIELD h="20" title="Fld16" w="150" x="290" y="150">fld16</TEXTFIELD>
			<TEXTFIELD h="20" title="Fld17" w="150" x="10" y="170">fld17</TEXTFIELD>
			<TEXTFIELD h="20" title="Fld18" w="150" x="290" y="170">fld18</TEXTFIELD>
			<TEXTFIELD h="20" title="Fld19" w="150" x="10" y="190">fld19</TEXTFIELD>
			<TEXTFIELD h="20" title="Narrative" w="430" x="10" y="210">narrative</TEXTFIELD>
		</FORM>

	</DESK>

	<DESK h="500" key="13" name="Bks30" splitloc="250" splittype="vert" w="585">
		<GRID gridfilter="true" key="1" keyfield="fld0" name="Bks30" pos="top" table="bks30">
			<TEXTFIELD title="Fld0" w="40">fld0</TEXTFIELD>
			<TEXTFIELD title="Fld1" w="40">fld1</TEXTFIELD>
			<TEXTFIELD title="Fld2" w="40">fld2</TEXTFIELD>
			<TEXTFIELD title="Fld3" w="40">fld3</TEXTFIELD>
			<TEXTFIELD title="Fld4" w="40">fld4</TEXTFIELD>
			<TEXTFIELD title="Fld5" w="40">fld5</TEXTFIELD>
			<TEXTFIELD title="Fld6" w="40">fld6</TEXTFIELD>
			<TEXTFIELD title="Fld7" w="40">fld7</TEXTFIELD>
			<TEXTFIELD title="Fld8" w="40">fld8</TEXTFIELD>
			<TEXTFIELD title="Fld9" w="40">fld9</TEXTFIELD>
			<TEXTFIELD title="Fld10" w="40">fld10</TEXTFIELD>
			<TEXTFIELD title="Fld11" w="40">fld11</TEXTFIELD>
			<TEXTFIELD title="Fld12" w="40">fld12</TEXTFIELD>
			<TEXTFIELD title="Fld13" w="40">fld13</TEXTFIELD>
			<TEXTFIELD title="Fld14" w="40">fld14</TEXTFIELD>
			<TEXTFIELD title="Fld15" w="40">fld15</TEXTFIELD>
			<TEXTFIELD title="Fld16" w="40">fld16</TEXTFIELD>
			<TEXTFIELD title="Fld17" w="40">fld17</TEXTFIELD>
			<TEXTFIELD title="Fld18" w="40">fld18</TEXTFIELD>
			<TEXTFIELD title="Fld19" w="40">fld19</TEXTFIELD>
			<TEXTFIELD title="Narrative" w="40">narrative</TEXTFIELD>
		</GRID>

		<FORM autofield="fld0" key="2" linkfield="fld0" linkkey="1" name="Bks30" pos="bottom" table="bks30">
			<TEXTFIELD h="20" title="Fld1" w="150" x="10" y="10">fld1</TEXTFIELD>
			<TEXTFIELD h="20" title="Fld2" w="150" x="290" y="10">fld2</TEXTFIELD>
			<TEXTFIELD h="20" title="Fld3" w="150" x="10" y="30">fld3</TEXTFIELD>
			<TEXTFIELD h="20" title="Fld4" w="150" x="290" y="30">fld4</TEXTFIELD>
			<TEXTFIELD h="20" title="Fld5" w="150" x="10" y="50">fld5</TEXTFIELD>
			<TEXTFIELD h="20" title="Fld6" w="150" x="290" y="50">fld6</TEXTFIELD>
			<TEXTFIELD h="20" title="Fld7" w="150" x="10" y="70">fld7</TEXTFIELD>
			<TEXTFIELD h="20" title="Fld8" w="150" x="290" y="70">fld8</TEXTFIELD>
			<TEXTFIELD h="20" title="Fld9" w="150" x="10" y="90">fld9</TEXTFIELD>
			<TEXTFIELD h="20" title="Fld10" w="150" x="290" y="90">fld10</TEXTFIELD>
			<TEXTFIELD h="20" title="Fld11" w="150" x="10" y="110">fld11</TEXTFIELD>
			<TEXTFIELD h="20" title="Fld12" w="150" x="290" y="110">fld12</TEXTFIELD>
			<TEXTFIELD h="20" title="Fld13" w="150" x="10" y="130">fld13</TEXTFIELD>
			<TEXTFIELD h="20" title="Fld14" w="150" x="290" y="130">fld14</TEXTFIELD>
			<TEXTFIELD h="20" title="Fld15" w="150" x="10" y="150">fld15</TEXTFIELD>
			<TEXTFIELD h="20" title="Fld16" w="150" x="290" y="150">fld16</TEXTFIELD>
			<TEXTFIELD h="20" title="Fld17" w="150" x="10" y="170">fld17</TEXTFIELD>
			<TEXTFIELD h="20" title="Fld18" w="150" x="290" y="170">fld18</TEXTFIELD>
			<TEXTFIELD h="20" title="Fld19" w="150" x="10" y="190">fld19</TEXTFIELD>
			<TEXTFIELD h="20" title="Narrative" w="430" x="10" y="210">narrative</TEXTFIELD>
		</FORM>

	</DESK>

	<DESK h="500" key="14" name="Bks39" splitloc="250" splittype="vert" w="585">
		<GRID gridfilter="true" key="1" keyfield="fld0" name="Bks39" pos="top" table="bks39">
			<TEXTFIELD title="Fld0" w="40">fld0</TEXTFIELD>
			<TEXTFIELD title="Fld1" w="40">fld1</TEXTFIELD>
			<TEXTFIELD title="Fld2" w="40">fld2</TEXTFIELD>
			<TEXTFIELD title="Fld3" w="40">fld3</TEXTFIELD>
			<TEXTFIELD title="Fld4" w="40">fld4</TEXTFIELD>
			<TEXTFIELD title="Fld5" w="40">fld5</TEXTFIELD>
			<TEXTFIELD title="Fld6" w="40">fld6</TEXTFIELD>
			<TEXTFIELD title="Fld7" w="40">fld7</TEXTFIELD>
			<TEXTFIELD title="Fld8" w="40">fld8</TEXTFIELD>
			<TEXTFIELD title="Fld9" w="40">fld9</TEXTFIELD>
			<TEXTFIELD title="Fld10" w="40">fld10</TEXTFIELD>
			<TEXTFIELD title="Fld11" w="40">fld11</TEXTFIELD>
			<TEXTFIELD title="Fld12" w="40">fld12</TEXTFIELD>
			<TEXTFIELD title="Fld13" w="40">fld13</TEXTFIELD>
			<TEXTFIELD title="Fld14" w="40">fld14</TEXTFIELD>
			<TEXTFIELD title="Fld15" w="40">fld15</TEXTFIELD>
			<TEXTFIELD title="Fld16" w="40">fld16</TEXTFIELD>
			<TEXTFIELD title="Fld17" w="40">fld17</TEXTFIELD>
			<TEXTFIELD title="Fld18" w="40">fld18</TEXTFIELD>
			<TEXTFIELD title="Fld19" w="40">fld19</TEXTFIELD>
			<TEXTFIELD title="Fld20" w="40">fld20</TEXTFIELD>
			<TEXTFIELD title="Narrative" w="40">narrative</TEXTFIELD>
		</GRID>

		<FORM autofield="fld0" key="2" linkfield="fld0" linkkey="1" name="Bks39" pos="bottom" table="bks39">
			<TEXTFIELD h="20" title="Fld1" w="150" x="10" y="10">fld1</TEXTFIELD>
			<TEXTFIELD h="20" title="Fld2" w="150" x="290" y="10">fld2</TEXTFIELD>
			<TEXTFIELD h="20" title="Fld3" w="150" x="10" y="30">fld3</TEXTFIELD>
			<TEXTFIELD h="20" title="Fld4" w="150" x="290" y="30">fld4</TEXTFIELD>
			<TEXTFIELD h="20" title="Fld5" w="150" x="10" y="50">fld5</TEXTFIELD>
			<TEXTFIELD h="20" title="Fld6" w="150" x="290" y="50">fld6</TEXTFIELD>
			<TEXTFIELD h="20" title="Fld7" w="150" x="10" y="70">fld7</TEXTFIELD>
			<TEXTFIELD h="20" title="Fld8" w="150" x="290" y="70">fld8</TEXTFIELD>
			<TEXTFIELD h="20" title="Fld9" w="150" x="10" y="90">fld9</TEXTFIELD>
			<TEXTFIELD h="20" title="Fld10" w="150" x="290" y="90">fld10</TEXTFIELD>
			<TEXTFIELD h="20" title="Fld11" w="150" x="10" y="110">fld11</TEXTFIELD>
			<TEXTFIELD h="20" title="Fld12" w="150" x="290" y="110">fld12</TEXTFIELD>
			<TEXTFIELD h="20" title="Fld13" w="150" x="10" y="130">fld13</TEXTFIELD>
			<TEXTFIELD h="20" title="Fld14" w="150" x="290" y="130">fld14</TEXTFIELD>
			<TEXTFIELD h="20" title="Fld15" w="150" x="10" y="150">fld15</TEXTFIELD>
			<TEXTFIELD h="20" title="Fld16" w="150" x="290" y="150">fld16</TEXTFIELD>
			<TEXTFIELD h="20" title="Fld17" w="150" x="10" y="170">fld17</TEXTFIELD>
			<TEXTFIELD h="20" title="Fld18" w="150" x="290" y="170">fld18</TEXTFIELD>
			<TEXTFIELD h="20" title="Fld19" w="150" x="10" y="190">fld19</TEXTFIELD>
			<TEXTFIELD h="20" title="Fld20" w="150" x="290" y="190">fld20</TEXTFIELD>
			<TEXTFIELD h="20" title="Narrative" w="430" x="10" y="210">narrative</TEXTFIELD>
		</FORM>

	</DESK>

	<DESK h="500" key="15" name="Bks42" splitloc="250" splittype="vert" w="585">
		<GRID gridfilter="true" key="1" keyfield="fld0" name="Bks42" pos="top" table="bks42">
			<TEXTFIELD title="Fld0" w="40">fld0</TEXTFIELD>
			<TEXTFIELD title="Fld1" w="40">fld1</TEXTFIELD>
			<TEXTFIELD title="Fld2" w="40">fld2</TEXTFIELD>
			<TEXTFIELD title="Fld3" w="40">fld3</TEXTFIELD>
			<TEXTFIELD title="Fld4" w="40">fld4</TEXTFIELD>
			<TEXTFIELD title="Fld5" w="40">fld5</TEXTFIELD>
			<TEXTFIELD title="Fld6" w="40">fld6</TEXTFIELD>
			<TEXTFIELD title="Fld7" w="40">fld7</TEXTFIELD>
			<TEXTFIELD title="Fld8" w="40">fld8</TEXTFIELD>
			<TEXTFIELD title="Fld9" w="40">fld9</TEXTFIELD>
			<TEXTFIELD title="Fld10" w="40">fld10</TEXTFIELD>
			<TEXTFIELD title="Fld11" w="40">fld11</TEXTFIELD>
			<TEXTFIELD title="Fld12" w="40">fld12</TEXTFIELD>
			<TEXTFIELD title="Fld13" w="40">fld13</TEXTFIELD>
			<TEXTFIELD title="Fld14" w="40">fld14</TEXTFIELD>
			<TEXTFIELD title="Fld15" w="40">fld15</TEXTFIELD>
			<TEXTFIELD title="Fld16" w="40">fld16</TEXTFIELD>
			<TEXTFIELD title="Fld17" w="40">fld17</TEXTFIELD>
			<TEXTFIELD title="Fld18" w="40">fld18</TEXTFIELD>
			<TEXTFIELD title="Fld19" w="40">fld19</TEXTFIELD>
			<TEXTFIELD title="Fld20" w="40">fld20</TEXTFIELD>
			<TEXTFIELD title="Fld21" w="40">fld21</TEXTFIELD>
			<TEXTFIELD title="Fld22" w="40">fld22</TEXTFIELD>
			<TEXTFIELD title="Narrative" w="40">narrative</TEXTFIELD>
		</GRID>

		<FORM autofield="fld0" key="2" linkfield="fld0" linkkey="1" name="Bks42" pos="bottom" table="bks42">
			<TEXTFIELD h="20" title="Fld1" w="150" x="10" y="10">fld1</TEXTFIELD>
			<TEXTFIELD h="20" title="Fld2" w="150" x="290" y="10">fld2</TEXTFIELD>
			<TEXTFIELD h="20" title="Fld3" w="150" x="10" y="30">fld3</TEXTFIELD>
			<TEXTFIELD h="20" title="Fld4" w="150" x="290" y="30">fld4</TEXTFIELD>
			<TEXTFIELD h="20" title="Fld5" w="150" x="10" y="50">fld5</TEXTFIELD>
			<TEXTFIELD h="20" title="Fld6" w="150" x="290" y="50">fld6</TEXTFIELD>
			<TEXTFIELD h="20" title="Fld7" w="150" x="10" y="70">fld7</TEXTFIELD>
			<TEXTFIELD h="20" title="Fld8" w="150" x="290" y="70">fld8</TEXTFIELD>
			<TEXTFIELD h="20" title="Fld9" w="150" x="10" y="90">fld9</TEXTFIELD>
			<TEXTFIELD h="20" title="Fld10" w="150" x="290" y="90">fld10</TEXTFIELD>
			<TEXTFIELD h="20" title="Fld11" w="150" x="10" y="110">fld11</TEXTFIELD>
			<TEXTFIELD h="20" title="Fld12" w="150" x="290" y="110">fld12</TEXTFIELD>
			<TEXTFIELD h="20" title="Fld13" w="150" x="10" y="130">fld13</TEXTFIELD>
			<TEXTFIELD h="20" title="Fld14" w="150" x="290" y="130">fld14</TEXTFIELD>
			<TEXTFIELD h="20" title="Fld15" w="150" x="10" y="150">fld15</TEXTFIELD>
			<TEXTFIELD h="20" title="Fld16" w="150" x="290" y="150">fld16</TEXTFIELD>
			<TEXTFIELD h="20" title="Fld17" w="150" x="10" y="170">fld17</TEXTFIELD>
			<TEXTFIELD h="20" title="Fld18" w="150" x="290" y="170">fld18</TEXTFIELD>
			<TEXTFIELD h="20" title="Fld19" w="150" x="10" y="190">fld19</TEXTFIELD>
			<TEXTFIELD h="20" title="Fld20" w="150" x="290" y="190">fld20</TEXTFIELD>
			<TEXTFIELD h="20" title="Fld21" w="150" x="10" y="210">fld21</TEXTFIELD>
			<TEXTFIELD h="20" title="Fld22" w="150" x="290" y="210">fld22</TEXTFIELD>
			<TEXTFIELD h="20" title="Narrative" w="430" x="10" y="230">narrative</TEXTFIELD>
		</FORM>

	</DESK>

	<DESK h="500" key="16" name="Bks45" splitloc="250" splittype="vert" w="585">
		<GRID gridfilter="true" key="1" keyfield="fld0" name="Bks45" pos="top" table="bks45">
			<TEXTFIELD title="Fld0" w="40">fld0</TEXTFIELD>
			<TEXTFIELD title="Fld1" w="40">fld1</TEXTFIELD>
			<TEXTFIELD title="Fld2" w="40">fld2</TEXTFIELD>
			<TEXTFIELD title="Fld3" w="40">fld3</TEXTFIELD>
			<TEXTFIELD title="Fld4" w="40">fld4</TEXTFIELD>
			<TEXTFIELD title="Fld5" w="40">fld5</TEXTFIELD>
			<TEXTFIELD title="Fld6" w="40">fld6</TEXTFIELD>
			<TEXTFIELD title="Fld7" w="40">fld7</TEXTFIELD>
			<TEXTFIELD title="Fld8" w="40">fld8</TEXTFIELD>
			<TEXTFIELD title="Fld9" w="40">fld9</TEXTFIELD>
			<TEXTFIELD title="Fld10" w="40">fld10</TEXTFIELD>
			<TEXTFIELD title="Fld11" w="40">fld11</TEXTFIELD>
			<TEXTFIELD title="Fld12" w="40">fld12</TEXTFIELD>
			<TEXTFIELD title="Fld13" w="40">fld13</TEXTFIELD>
			<TEXTFIELD title="Fld14" w="40">fld14</TEXTFIELD>
			<TEXTFIELD title="Narrative" w="40">narrative</TEXTFIELD>
		</GRID>

		<FORM autofield="fld0" key="2" linkfield="fld0" linkkey="1" name="Bks45" pos="bottom" table="bks45">
			<TEXTFIELD h="20" title="Fld1" w="150" x="10" y="10">fld1</TEXTFIELD>
			<TEXTFIELD h="20" title="Fld2" w="150" x="290" y="10">fld2</TEXTFIELD>
			<TEXTFIELD h="20" title="Fld3" w="150" x="10" y="30">fld3</TEXTFIELD>
			<TEXTFIELD h="20" title="Fld4" w="150" x="290" y="30">fld4</TEXTFIELD>
			<TEXTFIELD h="20" title="Fld5" w="150" x="10" y="50">fld5</TEXTFIELD>
			<TEXTFIELD h="20" title="Fld6" w="150" x="290" y="50">fld6</TEXTFIELD>
			<TEXTFIELD h="20" title="Fld7" w="150" x="10" y="70">fld7</TEXTFIELD>
			<TEXTFIELD h="20" title="Fld8" w="150" x="290" y="70">fld8</TEXTFIELD>
			<TEXTFIELD h="20" title="Fld9" w="150" x="10" y="90">fld9</TEXTFIELD>
			<TEXTFIELD h="20" title="Fld10" w="150" x="290" y="90">fld10</TEXTFIELD>
			<TEXTFIELD h="20" title="Fld11" w="150" x="10" y="110">fld11</TEXTFIELD>
			<TEXTFIELD h="20" title="Fld12" w="150" x="290" y="110">fld12</TEXTFIELD>
			<TEXTFIELD h="20" title="Fld13" w="150" x="10" y="130">fld13</TEXTFIELD>
			<TEXTFIELD h="20" title="Fld14" w="150" x="290" y="130">fld14</TEXTFIELD>
			<TEXTFIELD h="20" title="Narrative" w="430" x="10" y="150">narrative</TEXTFIELD>
		</FORM>

	</DESK>

	<DESK h="500" key="17" name="Bks46" splitloc="250" splittype="vert" w="585">
		<GRID gridfilter="true" key="1" keyfield="fld0" name="Bks46" pos="top" table="bks46">
			<TEXTFIELD title="Fld0" w="40">fld0</TEXTFIELD>
			<TEXTFIELD title="Fld1" w="40">fld1</TEXTFIELD>
			<TEXTFIELD title="Fld2" w="40">fld2</TEXTFIELD>
			<TEXTFIELD title="Fld3" w="40">fld3</TEXTFIELD>
			<TEXTFIELD title="Fld4" w="40">fld4</TEXTFIELD>
			<TEXTFIELD title="Fld5" w="40">fld5</TEXTFIELD>
			<TEXTFIELD title="Fld6" w="40">fld6</TEXTFIELD>
			<TEXTFIELD title="Fld7" w="40">fld7</TEXTFIELD>
			<TEXTFIELD title="Fld8" w="40">fld8</TEXTFIELD>
			<TEXTFIELD title="Fld9" w="40">fld9</TEXTFIELD>
			<TEXTFIELD title="Fld10" w="40">fld10</TEXTFIELD>
			<TEXTFIELD title="Narrative" w="40">narrative</TEXTFIELD>
		</GRID>

		<FORM autofield="fld0" key="2" linkfield="fld0" linkkey="1" name="Bks46" pos="bottom" table="bks46">
			<TEXTFIELD h="20" title="Fld1" w="150" x="10" y="10">fld1</TEXTFIELD>
			<TEXTFIELD h="20" title="Fld2" w="150" x="290" y="10">fld2</TEXTFIELD>
			<TEXTFIELD h="20" title="Fld3" w="150" x="10" y="30">fld3</TEXTFIELD>
			<TEXTFIELD h="20" title="Fld4" w="150" x="290" y="30">fld4</TEXTFIELD>
			<TEXTFIELD h="20" title="Fld5" w="150" x="10" y="50">fld5</TEXTFIELD>
			<TEXTFIELD h="20" title="Fld6" w="150" x="290" y="50">fld6</TEXTFIELD>
			<TEXTFIELD h="20" title="Fld7" w="150" x="10" y="70">fld7</TEXTFIELD>
			<TEXTFIELD h="20" title="Fld8" w="150" x="290" y="70">fld8</TEXTFIELD>
			<TEXTFIELD h="20" title="Fld9" w="150" x="10" y="90">fld9</TEXTFIELD>
			<TEXTFIELD h="20" title="Fld10" w="150" x="290" y="90">fld10</TEXTFIELD>
			<TEXTFIELD h="20" title="Narrative" w="430" x="10" y="110">narrative</TEXTFIELD>
		</FORM>

	</DESK>

	<DESK h="500" key="18" name="Bkt06" splitloc="250" splittype="vert" w="585">
		<GRID gridfilter="true" key="1" keyfield="fld0" name="Bkt06" pos="top" table="bkt06">
			<TEXTFIELD title="Fld0" w="40">fld0</TEXTFIELD>
			<TEXTFIELD title="Fld1" w="40">fld1</TEXTFIELD>
			<TEXTFIELD title="Fld2" w="40">fld2</TEXTFIELD>
			<TEXTFIELD title="Fld3" w="40">fld3</TEXTFIELD>
			<TEXTFIELD title="Fld4" w="40">fld4</TEXTFIELD>
			<TEXTFIELD title="Fld5" w="40">fld5</TEXTFIELD>
			<TEXTFIELD title="Fld6" w="40">fld6</TEXTFIELD>
			<TEXTFIELD title="Fld7" w="40">fld7</TEXTFIELD>
			<TEXTFIELD title="Fld8" w="40">fld8</TEXTFIELD>
			<TEXTFIELD title="Fld9" w="40">fld9</TEXTFIELD>
			<TEXTFIELD title="Fld10" w="40">fld10</TEXTFIELD>
			<TEXTFIELD title="Fld11" w="40">fld11</TEXTFIELD>
			<TEXTFIELD title="Fld12" w="40">fld12</TEXTFIELD>
			<TEXTFIELD title="Fld13" w="40">fld13</TEXTFIELD>
			<TEXTFIELD title="Fld14" w="40">fld14</TEXTFIELD>
			<TEXTFIELD title="Fld15" w="40">fld15</TEXTFIELD>
			<TEXTFIELD title="Fld16" w="40">fld16</TEXTFIELD>
			<TEXTFIELD title="Fld17" w="40">fld17</TEXTFIELD>
			<TEXTFIELD title="Fld18" w="40">fld18</TEXTFIELD>
			<TEXTFIELD title="Fld19" w="40">fld19</TEXTFIELD>
			<TEXTFIELD title="Fld20" w="40">fld20</TEXTFIELD>
			<TEXTFIELD title="Fld21" w="40">fld21</TEXTFIELD>
			<TEXTFIELD title="Fld22" w="40">fld22</TEXTFIELD>
			<TEXTFIELD title="Fld23" w="40">fld23</TEXTFIELD>
			<TEXTFIELD title="Fld24" w="40">fld24</TEXTFIELD>
			<TEXTFIELD title="Narrative" w="40">narrative</TEXTFIELD>
		</GRID>

		<FORM autofield="fld0" key="2" linkfield="fld0" linkkey="1" name="Bkt06" pos="bottom" table="bkt06">
			<TEXTFIELD h="20" title="Fld1" w="150" x="10" y="10">fld1</TEXTFIELD>
			<TEXTFIELD h="20" title="Fld2" w="150" x="290" y="10">fld2</TEXTFIELD>
			<TEXTFIELD h="20" title="Fld3" w="150" x="10" y="30">fld3</TEXTFIELD>
			<TEXTFIELD h="20" title="Fld4" w="150" x="290" y="30">fld4</TEXTFIELD>
			<TEXTFIELD h="20" title="Fld5" w="150" x="10" y="50">fld5</TEXTFIELD>
			<TEXTFIELD h="20" title="Fld6" w="150" x="290" y="50">fld6</TEXTFIELD>
			<TEXTFIELD h="20" title="Fld7" w="150" x="10" y="70">fld7</TEXTFIELD>
			<TEXTFIELD h="20" title="Fld8" w="150" x="290" y="70">fld8</TEXTFIELD>
			<TEXTFIELD h="20" title="Fld9" w="150" x="10" y="90">fld9</TEXTFIELD>
			<TEXTFIELD h="20" title="Fld10" w="150" x="290" y="90">fld10</TEXTFIELD>
			<TEXTFIELD h="20" title="Fld11" w="150" x="10" y="110">fld11</TEXTFIELD>
			<TEXTFIELD h="20" title="Fld12" w="150" x="290" y="110">fld12</TEXTFIELD>
			<TEXTFIELD h="20" title="Fld13" w="150" x="10" y="130">fld13</TEXTFIELD>
			<TEXTFIELD h="20" title="Fld14" w="150" x="290" y="130">fld14</TEXTFIELD>
			<TEXTFIELD h="20" title="Fld15" w="150" x="10" y="150">fld15</TEXTFIELD>
			<TEXTFIELD h="20" title="Fld16" w="150" x="290" y="150">fld16</TEXTFIELD>
			<TEXTFIELD h="20" title="Fld17" w="150" x="10" y="170">fld17</TEXTFIELD>
			<TEXTFIELD h="20" title="Fld18" w="150" x="290" y="170">fld18</TEXTFIELD>
			<TEXTFIELD h="20" title="Fld19" w="150" x="10" y="190">fld19</TEXTFIELD>
			<TEXTFIELD h="20" title="Fld20" w="150" x="290" y="190">fld20</TEXTFIELD>
			<TEXTFIELD h="20" title="Fld21" w="150" x="10" y="210">fld21</TEXTFIELD>
			<TEXTFIELD h="20" title="Fld22" w="150" x="290" y="210">fld22</TEXTFIELD>
			<TEXTFIELD h="20" title="Fld23" w="150" x="10" y="230">fld23</TEXTFIELD>
			<TEXTFIELD h="20" title="Fld24" w="150" x="290" y="230">fld24</TEXTFIELD>
			<TEXTFIELD h="20" title="Narrative" w="430" x="10" y="250">narrative</TEXTFIELD>
		</FORM>

	</DESK>

	<DESK h="500" key="19" name="Bmd75" splitloc="250" splittype="vert" w="585">
		<GRID gridfilter="true" key="1" keyfield="fld0" name="Bmd75" pos="top" table="bmd75">
			<TEXTFIELD title="Fld0" w="40">fld0</TEXTFIELD>
			<TEXTFIELD title="Fld1" w="40">fld1</TEXTFIELD>
			<TEXTFIELD title="Fld2" w="40">fld2</TEXTFIELD>
			<TEXTFIELD title="Fld3" w="40">fld3</TEXTFIELD>
			<TEXTFIELD title="Fld4" w="40">fld4</TEXTFIELD>
			<TEXTFIELD title="Fld5" w="40">fld5</TEXTFIELD>
			<TEXTFIELD title="Fld6" w="40">fld6</TEXTFIELD>
			<TEXTFIELD title="Fld7" w="40">fld7</TEXTFIELD>
			<TEXTFIELD title="Fld8" w="40">fld8</TEXTFIELD>
			<TEXTFIELD title="Fld9" w="40">fld9</TEXTFIELD>
			<TEXTFIELD title="Fld10" w="40">fld10</TEXTFIELD>
			<TEXTFIELD title="Fld11" w="40">fld11</TEXTFIELD>
			<TEXTFIELD title="Fld12" w="40">fld12</TEXTFIELD>
			<TEXTFIELD title="Fld13" w="40">fld13</TEXTFIELD>
			<TEXTFIELD title="Fld14" w="40">fld14</TEXTFIELD>
			<TEXTFIELD title="Fld15" w="40">fld15</TEXTFIELD>
			<TEXTFIELD title="Fld16" w="40">fld16</TEXTFIELD>
			<TEXTFIELD title="Fld17" w="40">fld17</TEXTFIELD>
			<TEXTFIELD title="Fld18" w="40">fld18</TEXTFIELD>
			<TEXTFIELD title="Fld19" w="40">fld19</TEXTFIELD>
			<TEXTFIELD title="Fld20" w="40">fld20</TEXTFIELD>
			<TEXTFIELD title="Narrative" w="40">narrative</TEXTFIELD>
		</GRID>

		<FORM autofield="fld0" key="2" linkfield="fld0" linkkey="1" name="Bmd75" pos="bottom" table="bmd75">
			<TEXTFIELD h="20" title="Fld1" w="150" x="10" y="10">fld1</TEXTFIELD>
			<TEXTFIELD h="20" title="Fld2" w="150" x="290" y="10">fld2</TEXTFIELD>
			<TEXTFIELD h="20" title="Fld3" w="150" x="10" y="30">fld3</TEXTFIELD>
			<TEXTFIELD h="20" title="Fld4" w="150" x="290" y="30">fld4</TEXTFIELD>
			<TEXTFIELD h="20" title="Fld5" w="150" x="10" y="50">fld5</TEXTFIELD>
			<TEXTFIELD h="20" title="Fld6" w="150" x="290" y="50">fld6</TEXTFIELD>
			<TEXTFIELD h="20" title="Fld7" w="150" x="10" y="70">fld7</TEXTFIELD>
			<TEXTFIELD h="20" title="Fld8" w="150" x="290" y="70">fld8</TEXTFIELD>
			<TEXTFIELD h="20" title="Fld9" w="150" x="10" y="90">fld9</TEXTFIELD>
			<TEXTFIELD h="20" title="Fld10" w="150" x="290" y="90">fld10</TEXTFIELD>
			<TEXTFIELD h="20" title="Fld11" w="150" x="10" y="110">fld11</TEXTFIELD>
			<TEXTFIELD h="20" title="Fld12" w="150" x="290" y="110">fld12</TEXTFIELD>
			<TEXTFIELD h="20" title="Fld13" w="150" x="10" y="130">fld13</TEXTFIELD>
			<TEXTFIELD h="20" title="Fld14" w="150" x="290" y="130">fld14</TEXTFIELD>
			<TEXTFIELD h="20" title="Fld15" w="150" x="10" y="150">fld15</TEXTFIELD>
			<TEXTFIELD h="20" title="Fld16" w="150" x="290" y="150">fld16</TEXTFIELD>
			<TEXTFIELD h="20" title="Fld17" w="150" x="10" y="170">fld17</TEXTFIELD>
			<TEXTFIELD h="20" title="Fld18" w="150" x="290" y="170">fld18</TEXTFIELD>
			<TEXTFIELD h="20" title="Fld19" w="150" x="10" y="190">fld19</TEXTFIELD>
			<TEXTFIELD h="20" title="Fld20" w="150" x="290" y="190">fld20</TEXTFIELD>
			<TEXTFIELD h="20" title="Narrative" w="430" x="10" y="210">narrative</TEXTFIELD>
		</FORM>

	</DESK>

	<DESK h="500" key="20" name="Bmd76" splitloc="250" splittype="vert" w="585">
		<GRID gridfilter="true" key="1" keyfield="fld0" name="Bmd76" pos="top" table="bmd76">
			<TEXTFIELD title="Fld0" w="40">fld0</TEXTFIELD>
			<TEXTFIELD title="Fld1" w="40">fld1</TEXTFIELD>
			<TEXTFIELD title="Fld2" w="40">fld2</TEXTFIELD>
			<TEXTFIELD title="Fld3" w="40">fld3</TEXTFIELD>
			<TEXTFIELD title="Fld4" w="40">fld4</TEXTFIELD>
			<TEXTFIELD title="Fld5" w="40">fld5</TEXTFIELD>
			<TEXTFIELD title="Fld6" w="40">fld6</TEXTFIELD>
			<TEXTFIELD title="Fld7" w="40">fld7</TEXTFIELD>
			<TEXTFIELD title="Fld8" w="40">fld8</TEXTFIELD>
			<TEXTFIELD title="Fld9" w="40">fld9</TEXTFIELD>
			<TEXTFIELD title="Fld10" w="40">fld10</TEXTFIELD>
			<TEXTFIELD title="Narrative" w="40">narrative</TEXTFIELD>
		</GRID>

		<FORM autofield="fld0" key="2" linkfield="fld0" linkkey="1" name="Bmd76" pos="bottom" table="bmd76">
			<TEXTFIELD h="20" title="Fld1" w="150" x="10" y="10">fld1</TEXTFIELD>
			<TEXTFIELD h="20" title="Fld2" w="150" x="290" y="10">fld2</TEXTFIELD>
			<TEXTFIELD h="20" title="Fld3" w="150" x="10" y="30">fld3</TEXTFIELD>
			<TEXTFIELD h="20" title="Fld4" w="150" x="290" y="30">fld4</TEXTFIELD>
			<TEXTFIELD h="20" title="Fld5" w="150" x="10" y="50">fld5</TEXTFIELD>
			<TEXTFIELD h="20" title="Fld6" w="150" x="290" y="50">fld6</TEXTFIELD>
			<TEXTFIELD h="20" title="Fld7" w="150" x="10" y="70">fld7</TEXTFIELD>
			<TEXTFIELD h="20" title="Fld8" w="150" x="290" y="70">fld8</TEXTFIELD>
			<TEXTFIELD h="20" title="Fld9" w="150" x="10" y="90">fld9</TEXTFIELD>
			<TEXTFIELD h="20" title="Fld10" w="150" x="290" y="90">fld10</TEXTFIELD>
			<TEXTFIELD h="20" title="Narrative" w="430" x="10" y="110">narrative</TEXTFIELD>
		</FORM>

	</DESK>

	<DESK h="500" key="21" name="Bmp70" splitloc="250" splittype="vert" w="585">
		<GRID gridfilter="true" key="1" keyfield="fld0" name="Bmp70" pos="top" table="bmp70">
			<TEXTFIELD title="Fld0" w="40">fld0</TEXTFIELD>
			<TEXTFIELD title="Fld1" w="40">fld1</TEXTFIELD>
			<TEXTFIELD title="Fld2" w="40">fld2</TEXTFIELD>
			<TEXTFIELD title="Fld3" w="40">fld3</TEXTFIELD>
			<TEXTFIELD title="Fld4" w="40">fld4</TEXTFIELD>
			<TEXTFIELD title="Fld5" w="40">fld5</TEXTFIELD>
			<TEXTFIELD title="Fld6" w="40">fld6</TEXTFIELD>
			<TEXTFIELD title="Fld7" w="40">fld7</TEXTFIELD>
			<TEXTFIELD title="Fld8" w="40">fld8</TEXTFIELD>
			<TEXTFIELD title="Fld9" w="40">fld9</TEXTFIELD>
			<TEXTFIELD title="Fld10" w="40">fld10</TEXTFIELD>
			<TEXTFIELD title="Narrative" w="40">narrative</TEXTFIELD>
		</GRID>

		<FORM autofield="fld0" key="2" linkfield="fld0" linkkey="1" name="Bmp70" pos="bottom" table="bmp70">
			<TEXTFIELD h="20" title="Fld1" w="150" x="10" y="10">fld1</TEXTFIELD>
			<TEXTFIELD h="20" title="Fld2" w="150" x="290" y="10">fld2</TEXTFIELD>
			<TEXTFIELD h="20" title="Fld3" w="150" x="10" y="30">fld3</TEXTFIELD>
			<TEXTFIELD h="20" title="Fld4" w="150" x="290" y="30">fld4</TEXTFIELD>
			<TEXTFIELD h="20" title="Fld5" w="150" x="10" y="50">fld5</TEXTFIELD>
			<TEXTFIELD h="20" title="Fld6" w="150" x="290" y="50">fld6</TEXTFIELD>
			<TEXTFIELD h="20" title="Fld7" w="150" x="10" y="70">fld7</TEXTFIELD>
			<TEXTFIELD h="20" title="Fld8" w="150" x="290" y="70">fld8</TEXTFIELD>
			<TEXTFIELD h="20" title="Fld9" w="150" x="10" y="90">fld9</TEXTFIELD>
			<TEXTFIELD h="20" title="Fld10" w="150" x="290" y="90">fld10</TEXTFIELD>
			<TEXTFIELD h="20" title="Narrative" w="430" x="10" y="110">narrative</TEXTFIELD>
		</FORM>

	</DESK>

	<DESK h="500" key="22" name="Bmp71" splitloc="250" splittype="vert" w="585">
		<GRID gridfilter="true" key="1" keyfield="fld0" name="Bmp71" pos="top" table="bmp71">
			<TEXTFIELD title="Fld0" w="40">fld0</TEXTFIELD>
			<TEXTFIELD title="Fld1" w="40">fld1</TEXTFIELD>
			<TEXTFIELD title="Fld2" w="40">fld2</TEXTFIELD>
			<TEXTFIELD title="Fld3" w="40">fld3</TEXTFIELD>
			<TEXTFIELD title="Fld4" w="40">fld4</TEXTFIELD>
			<TEXTFIELD title="Fld5" w="40">fld5</TEXTFIELD>
			<TEXTFIELD title="Fld6" w="40">fld6</TEXTFIELD>
			<TEXTFIELD title="Fld7" w="40">fld7</TEXTFIELD>
			<TEXTFIELD title="Fld8" w="40">fld8</TEXTFIELD>
			<TEXTFIELD title="Fld9" w="40">fld9</TEXTFIELD>
			<TEXTFIELD title="Fld10" w="40">fld10</TEXTFIELD>
			<TEXTFIELD title="Fld11" w="40">fld11</TEXTFIELD>
			<TEXTFIELD title="Fld12" w="40">fld12</TEXTFIELD>
			<TEXTFIELD title="Fld13" w="40">fld13</TEXTFIELD>
			<TEXTFIELD title="Fld14" w="40">fld14</TEXTFIELD>
			<TEXTFIELD title="Fld15" w="40">fld15</TEXTFIELD>
			<TEXTFIELD title="Fld16" w="40">fld16</TEXTFIELD>
			<TEXTFIELD title="Narrative" w="40">narrative</TEXTFIELD>
		</GRID>

		<FORM autofield="fld0" key="2" linkfield="fld0" linkkey="1" name="Bmp71" pos="bottom" table="bmp71">
			<TEXTFIELD h="20" title="Fld1" w="150" x="10" y="10">fld1</TEXTFIELD>
			<TEXTFIELD h="20" title="Fld2" w="150" x="290" y="10">fld2</TEXTFIELD>
			<TEXTFIELD h="20" title="Fld3" w="150" x="10" y="30">fld3</TEXTFIELD>
			<TEXTFIELD h="20" title="Fld4" w="150" x="290" y="30">fld4</TEXTFIELD>
			<TEXTFIELD h="20" title="Fld5" w="150" x="10" y="50">fld5</TEXTFIELD>
			<TEXTFIELD h="20" title="Fld6" w="150" x="290" y="50">fld6</TEXTFIELD>
			<TEXTFIELD h="20" title="Fld7" w="150" x="10" y="70">fld7</TEXTFIELD>
			<TEXTFIELD h="20" title="Fld8" w="150" x="290" y="70">fld8</TEXTFIELD>
			<TEXTFIELD h="20" title="Fld9" w="150" x="10" y="90">fld9</TEXTFIELD>
			<TEXTFIELD h="20" title="Fld10" w="150" x="290" y="90">fld10</TEXTFIELD>
			<TEXTFIELD h="20" title="Fld11" w="150" x="10" y="110">fld11</TEXTFIELD>
			<TEXTFIELD h="20" title="Fld12" w="150" x="290" y="110">fld12</TEXTFIELD>
			<TEXTFIELD h="20" title="Fld13" w="150" x="10" y="130">fld13</TEXTFIELD>
			<TEXTFIELD h="20" title="Fld14" w="150" x="290" y="130">fld14</TEXTFIELD>
			<TEXTFIELD h="20" title="Fld15" w="150" x="10" y="150">fld15</TEXTFIELD>
			<TEXTFIELD h="20" title="Fld16" w="150" x="290" y="150">fld16</TEXTFIELD>
			<TEXTFIELD h="20" title="Narrative" w="430" x="10" y="170">narrative</TEXTFIELD>
		</FORM>

	</DESK>

	<DESK h="500" key="23" name="Bmp72" splitloc="250" splittype="vert" w="585">
		<GRID gridfilter="true" key="1" keyfield="fld0" name="Bmp72" pos="top" table="bmp72">
			<TEXTFIELD title="Fld0" w="40">fld0</TEXTFIELD>
			<TEXTFIELD title="Fld1" w="40">fld1</TEXTFIELD>
			<TEXTFIELD title="Fld2" w="40">fld2</TEXTFIELD>
			<TEXTFIELD title="Fld3" w="40">fld3</TEXTFIELD>
			<TEXTFIELD title="Fld4" w="40">fld4</TEXTFIELD>
			<TEXTFIELD title="Fld5" w="40">fld5</TEXTFIELD>
			<TEXTFIELD title="Fld6" w="40">fld6</TEXTFIELD>
			<TEXTFIELD title="Fld7" w="40">fld7</TEXTFIELD>
			<TEXTFIELD title="Fld8" w="40">fld8</TEXTFIELD>
			<TEXTFIELD title="Fld9" w="40">fld9</TEXTFIELD>
			<TEXTFIELD title="Narrative" w="40">narrative</TEXTFIELD>
		</GRID>

		<FORM autofield="fld0" key="2" linkfield="fld0" linkkey="1" name="Bmp72" pos="bottom" table="bmp72">
			<TEXTFIELD h="20" title="Fld1" w="150" x="10" y="10">fld1</TEXTFIELD>
			<TEXTFIELD h="20" title="Fld2" w="150" x="290" y="10">fld2</TEXTFIELD>
			<TEXTFIELD h="20" title="Fld3" w="150" x="10" y="30">fld3</TEXTFIELD>
			<TEXTFIELD h="20" title="Fld4" w="150" x="290" y="30">fld4</TEXTFIELD>
			<TEXTFIELD h="20" title="Fld5" w="150" x="10" y="50">fld5</TEXTFIELD>
			<TEXTFIELD h="20" title="Fld6" w="150" x="290" y="50">fld6</TEXTFIELD>
			<TEXTFIELD h="20" title="Fld7" w="150" x="10" y="70">fld7</TEXTFIELD>
			<TEXTFIELD h="20" title="Fld8" w="150" x="290" y="70">fld8</TEXTFIELD>
			<TEXTFIELD h="20" title="Fld9" w="150" x="10" y="90">fld9</TEXTFIELD>
			<TEXTFIELD h="20" title="Narrative" w="430" x="10" y="110">narrative</TEXTFIELD>
		</FORM>

	</DESK>

	<DESK h="500" key="24" name="Bmp73" splitloc="250" splittype="vert" w="585">
		<GRID gridfilter="true" key="1" keyfield="fld0" name="Bmp73" pos="top" table="bmp73">
			<TEXTFIELD title="Fld0" w="40">fld0</TEXTFIELD>
			<TEXTFIELD title="Fld1" w="40">fld1</TEXTFIELD>
			<TEXTFIELD title="Fld2" w="40">fld2</TEXTFIELD>
			<TEXTFIELD title="Fld3" w="40">fld3</TEXTFIELD>
			<TEXTFIELD title="Fld4" w="40">fld4</TEXTFIELD>
			<TEXTFIELD title="Fld5" w="40">fld5</TEXTFIELD>
			<TEXTFIELD title="Fld6" w="40">fld6</TEXTFIELD>
			<TEXTFIELD title="Fld7" w="40">fld7</TEXTFIELD>
			<TEXTFIELD title="Fld8" w="40">fld8</TEXTFIELD>
			<TEXTFIELD title="Fld9" w="40">fld9</TEXTFIELD>
			<TEXTFIELD title="Narrative" w="40">narrative</TEXTFIELD>
		</GRID>

		<FORM autofield="fld0" key="2" linkfield="fld0" linkkey="1" name="Bmp73" pos="bottom" table="bmp73">
			<TEXTFIELD h="20" title="Fld1" w="150" x="10" y="10">fld1</TEXTFIELD>
			<TEXTFIELD h="20" title="Fld2" w="150" x="290" y="10">fld2</TEXTFIELD>
			<TEXTFIELD h="20" title="Fld3" w="150" x="10" y="30">fld3</TEXTFIELD>
			<TEXTFIELD h="20" title="Fld4" w="150" x="290" y="30">fld4</TEXTFIELD>
			<TEXTFIELD h="20" title="Fld5" w="150" x="10" y="50">fld5</TEXTFIELD>
			<TEXTFIELD h="20" title="Fld6" w="150" x="290" y="50">fld6</TEXTFIELD>
			<TEXTFIELD h="20" title="Fld7" w="150" x="10" y="70">fld7</TEXTFIELD>
			<TEXTFIELD h="20" title="Fld8" w="150" x="290" y="70">fld8</TEXTFIELD>
			<TEXTFIELD h="20" title="Fld9" w="150" x="10" y="90">fld9</TEXTFIELD>
			<TEXTFIELD h="20" title="Narrative" w="430" x="10" y="110">narrative</TEXTFIELD>
		</FORM>

	</DESK>

	<DESK h="500" key="25" name="Bmp74" splitloc="250" splittype="vert" w="585">
		<GRID gridfilter="true" key="1" keyfield="fld0" name="Bmp74" pos="top" table="bmp74">
			<TEXTFIELD title="Fld0" w="40">fld0</TEXTFIELD>
			<TEXTFIELD title="Fld1" w="40">fld1</TEXTFIELD>
			<TEXTFIELD title="Fld2" w="40">fld2</TEXTFIELD>
			<TEXTFIELD title="Fld3" w="40">fld3</TEXTFIELD>
			<TEXTFIELD title="Fld4" w="40">fld4</TEXTFIELD>
			<TEXTFIELD title="Fld5" w="40">fld5</TEXTFIELD>
			<TEXTFIELD title="Fld6" w="40">fld6</TEXTFIELD>
			<TEXTFIELD title="Fld7" w="40">fld7</TEXTFIELD>
			<TEXTFIELD title="Fld8" w="40">fld8</TEXTFIELD>
			<TEXTFIELD title="Fld9" w="40">fld9</TEXTFIELD>
			<TEXTFIELD title="Fld10" w="40">fld10</TEXTFIELD>
			<TEXTFIELD title="Narrative" w="40">narrative</TEXTFIELD>
		</GRID>

		<FORM autofield="fld0" key="2" linkfield="fld0" linkkey="1" name="Bmp74" pos="bottom" table="bmp74">
			<TEXTFIELD h="20" title="Fld1" w="150" x="10" y="10">fld1</TEXTFIELD>
			<TEXTFIELD h="20" title="Fld2" w="150" x="290" y="10">fld2</TEXTFIELD>
			<TEXTFIELD h="20" title="Fld3" w="150" x="10" y="30">fld3</TEXTFIELD>
			<TEXTFIELD h="20" title="Fld4" w="150" x="290" y="30">fld4</TEXTFIELD>
			<TEXTFIELD h="20" title="Fld5" w="150" x="10" y="50">fld5</TEXTFIELD>
			<TEXTFIELD h="20" title="Fld6" w="150" x="290" y="50">fld6</TEXTFIELD>
			<TEXTFIELD h="20" title="Fld7" w="150" x="10" y="70">fld7</TEXTFIELD>
			<TEXTFIELD h="20" title="Fld8" w="150" x="290" y="70">fld8</TEXTFIELD>
			<TEXTFIELD h="20" title="Fld9" w="150" x="10" y="90">fld9</TEXTFIELD>
			<TEXTFIELD h="20" title="Fld10" w="150" x="290" y="90">fld10</TEXTFIELD>
			<TEXTFIELD h="20" title="Narrative" w="430" x="10" y="110">narrative</TEXTFIELD>
		</FORM>

	</DESK>

	<DESK h="500" key="26" name="Bmp77" splitloc="250" splittype="vert" w="585">
		<GRID gridfilter="true" key="1" keyfield="fld0" name="Bmp77" pos="top" table="bmp77">
			<TEXTFIELD title="Fld0" w="40">fld0</TEXTFIELD>
			<TEXTFIELD title="Fld1" w="40">fld1</TEXTFIELD>
			<TEXTFIELD title="Fld2" w="40">fld2</TEXTFIELD>
			<TEXTFIELD title="Fld3" w="40">fld3</TEXTFIELD>
			<TEXTFIELD title="Fld4" w="40">fld4</TEXTFIELD>
			<TEXTFIELD title="Fld5" w="40">fld5</TEXTFIELD>
			<TEXTFIELD title="Fld6" w="40">fld6</TEXTFIELD>
			<TEXTFIELD title="Fld7" w="40">fld7</TEXTFIELD>
			<TEXTFIELD title="Fld8" w="40">fld8</TEXTFIELD>
			<TEXTFIELD title="Fld9" w="40">fld9</TEXTFIELD>
			<TEXTFIELD title="Fld10" w="40">fld10</TEXTFIELD>
			<TEXTFIELD title="Fld11" w="40">fld11</TEXTFIELD>
			<TEXTFIELD title="Fld12" w="40">fld12</TEXTFIELD>
			<TEXTFIELD title="Narrative" w="40">narrative</TEXTFIELD>
		</GRID>

		<FORM autofield="fld0" key="2" linkfield="fld0" linkkey="1" name="Bmp77" pos="bottom" table="bmp77">
			<TEXTFIELD h="20" title="Fld1" w="150" x="10" y="10">fld1</TEXTFIELD>
			<TEXTFIELD h="20" title="Fld2" w="150" x="290" y="10">fld2</TEXTFIELD>
			<TEXTFIELD h="20" title="Fld3" w="150" x="10" y="30">fld3</TEXTFIELD>
			<TEXTFIELD h="20" title="Fld4" w="150" x="290" y="30">fld4</TEXTFIELD>
			<TEXTFIELD h="20" title="Fld5" w="150" x="10" y="50">fld5</TEXTFIELD>
			<TEXTFIELD h="20" title="Fld6" w="150" x="290" y="50">fld6</TEXTFIELD>
			<TEXTFIELD h="20" title="Fld7" w="150" x="10" y="70">fld7</TEXTFIELD>
			<TEXTFIELD h="20" title="Fld8" w="150" x="290" y="70">fld8</TEXTFIELD>
			<TEXTFIELD h="20" title="Fld9" w="150" x="10" y="90">fld9</TEXTFIELD>
			<TEXTFIELD h="20" title="Fld10" w="150" x="290" y="90">fld10</TEXTFIELD>
			<TEXTFIELD h="20" title="Fld11" w="150" x="10" y="110">fld11</TEXTFIELD>
			<TEXTFIELD h="20" title="Fld12" w="150" x="290" y="110">fld12</TEXTFIELD>
			<TEXTFIELD h="20" title="Narrative" w="430" x="10" y="130">narrative</TEXTFIELD>
		</FORM>

	</DESK>

	<DESK h="500" key="27" name="Bmp78" splitloc="250" splittype="vert" w="585">
		<GRID gridfilter="true" key="1" keyfield="fld0" name="Bmp78" pos="top" table="bmp78">
			<TEXTFIELD title="Fld0" w="40">fld0</TEXTFIELD>
			<TEXTFIELD title="Fld1" w="40">fld1</TEXTFIELD>
			<TEXTFIELD title="Fld2" w="40">fld2</TEXTFIELD>
			<TEXTFIELD title="Fld3" w="40">fld3</TEXTFIELD>
			<TEXTFIELD title="Fld4" w="40">fld4</TEXTFIELD>
			<TEXTFIELD title="Fld5" w="40">fld5</TEXTFIELD>
			<TEXTFIELD title="Fld6" w="40">fld6</TEXTFIELD>
			<TEXTFIELD title="Fld7" w="40">fld7</TEXTFIELD>
			<TEXTFIELD title="Fld8" w="40">fld8</TEXTFIELD>
			<TEXTFIELD title="Fld9" w="40">fld9</TEXTFIELD>
			<TEXTFIELD title="Fld10" w="40">fld10</TEXTFIELD>
			<TEXTFIELD title="Fld11" w="40">fld11</TEXTFIELD>
			<TEXTFIELD title="Fld12" w="40">fld12</TEXTFIELD>
			<TEXTFIELD title="Narrative" w="40">narrative</TEXTFIELD>
		</GRID>

		<FORM autofield="fld0" key="2" linkfield="fld0" linkkey="1" name="Bmp78" pos="bottom" table="bmp78">
			<TEXTFIELD h="20" title="Fld1" w="150" x="10" y="10">fld1</TEXTFIELD>
			<TEXTFIELD h="20" title="Fld2" w="150" x="290" y="10">fld2</TEXTFIELD>
			<TEXTFIELD h="20" title="Fld3" w="150" x="10" y="30">fld3</TEXTFIELD>
			<TEXTFIELD h="20" title="Fld4" w="150" x="290" y="30">fld4</TEXTFIELD>
			<TEXTFIELD h="20" title="Fld5" w="150" x="10" y="50">fld5</TEXTFIELD>
			<TEXTFIELD h="20" title="Fld6" w="150" x="290" y="50">fld6</TEXTFIELD>
			<TEXTFIELD h="20" title="Fld7" w="150" x="10" y="70">fld7</TEXTFIELD>
			<TEXTFIELD h="20" title="Fld8" w="150" x="290" y="70">fld8</TEXTFIELD>
			<TEXTFIELD h="20" title="Fld9" w="150" x="10" y="90">fld9</TEXTFIELD>
			<TEXTFIELD h="20" title="Fld10" w="150" x="290" y="90">fld10</TEXTFIELD>
			<TEXTFIELD h="20" title="Fld11" w="150" x="10" y="110">fld11</TEXTFIELD>
			<TEXTFIELD h="20" title="Fld12" w="150" x="290" y="110">fld12</TEXTFIELD>
			<TEXTFIELD h="20" title="Narrative" w="430" x="10" y="130">narrative</TEXTFIELD>
		</FORM>

	</DESK>

	<DESK h="500" key="28" name="Boh03" splitloc="250" splittype="vert" w="585">
		<GRID gridfilter="true" key="1" keyfield="fld0" name="Boh03" pos="top" table="boh03">
			<TEXTFIELD title="Fld0" w="40">fld0</TEXTFIELD>
			<TEXTFIELD title="Fld1" w="40">fld1</TEXTFIELD>
			<TEXTFIELD title="Fld2" w="40">fld2</TEXTFIELD>
			<TEXTFIELD title="Fld3" w="40">fld3</TEXTFIELD>
			<TEXTFIELD title="Fld4" w="40">fld4</TEXTFIELD>
			<TEXTFIELD title="Fld5" w="40">fld5</TEXTFIELD>
			<TEXTFIELD title="Fld6" w="40">fld6</TEXTFIELD>
			<TEXTFIELD title="Fld7" w="40">fld7</TEXTFIELD>
			<TEXTFIELD title="Fld8" w="40">fld8</TEXTFIELD>
			<TEXTFIELD title="Fld9" w="40">fld9</TEXTFIELD>
			<TEXTFIELD title="Narrative" w="40">narrative</TEXTFIELD>
		</GRID>

		<FORM autofield="fld0" key="2" linkfield="fld0" linkkey="1" name="Boh03" pos="bottom" table="boh03">
			<TEXTFIELD h="20" title="Fld1" w="150" x="10" y="10">fld1</TEXTFIELD>
			<TEXTFIELD h="20" title="Fld2" w="150" x="290" y="10">fld2</TEXTFIELD>
			<TEXTFIELD h="20" title="Fld3" w="150" x="10" y="30">fld3</TEXTFIELD>
			<TEXTFIELD h="20" title="Fld4" w="150" x="290" y="30">fld4</TEXTFIELD>
			<TEXTFIELD h="20" title="Fld5" w="150" x="10" y="50">fld5</TEXTFIELD>
			<TEXTFIELD h="20" title="Fld6" w="150" x="290" y="50">fld6</TEXTFIELD>
			<TEXTFIELD h="20" title="Fld7" w="150" x="10" y="70">fld7</TEXTFIELD>
			<TEXTFIELD h="20" title="Fld8" w="150" x="290" y="70">fld8</TEXTFIELD>
			<TEXTFIELD h="20" title="Fld9" w="150" x="10" y="90">fld9</TEXTFIELD>
			<TEXTFIELD h="20" title="Narrative" w="430" x="10" y="110">narrative</TEXTFIELD>
		</FORM>

	</DESK>

	<DESK h="500" key="29" name="Bot93" splitloc="250" splittype="vert" w="585">
		<GRID gridfilter="true" key="1" keyfield="fld0" name="Bot93" pos="top" table="bot93">
			<TEXTFIELD title="Fld0" w="40">fld0</TEXTFIELD>
			<TEXTFIELD title="Fld1" w="40">fld1</TEXTFIELD>
			<TEXTFIELD title="Fld2" w="40">fld2</TEXTFIELD>
			<TEXTFIELD title="Fld3" w="40">fld3</TEXTFIELD>
			<TEXTFIELD title="Fld4" w="40">fld4</TEXTFIELD>
			<TEXTFIELD title="Fld5" w="40">fld5</TEXTFIELD>
			<TEXTFIELD title="Fld6" w="40">fld6</TEXTFIELD>
			<TEXTFIELD title="Fld7" w="40">fld7</TEXTFIELD>
			<TEXTFIELD title="Fld8" w="40">fld8</TEXTFIELD>
			<TEXTFIELD title="Fld9" w="40">fld9</TEXTFIELD>
			<TEXTFIELD title="Fld10" w="40">fld10</TEXTFIELD>
			<TEXTFIELD title="Fld11" w="40">fld11</TEXTFIELD>
			<TEXTFIELD title="Fld12" w="40">fld12</TEXTFIELD>
			<TEXTFIELD title="Fld13" w="40">fld13</TEXTFIELD>
			<TEXTFIELD title="Fld14" w="40">fld14</TEXTFIELD>
			<TEXTFIELD title="Fld15" w="40">fld15</TEXTFIELD>
			<TEXTFIELD title="Fld16" w="40">fld16</TEXTFIELD>
			<TEXTFIELD title="Narrative" w="40">narrative</TEXTFIELD>
		</GRID>

		<FORM autofield="fld0" key="2" linkfield="fld0" linkkey="1" name="Bot93" pos="bottom" table="bot93">
			<TEXTFIELD h="20" title="Fld1" w="150" x="10" y="10">fld1</TEXTFIELD>
			<TEXTFIELD h="20" title="Fld2" w="150" x="290" y="10">fld2</TEXTFIELD>
			<TEXTFIELD h="20" title="Fld3" w="150" x="10" y="30">fld3</TEXTFIELD>
			<TEXTFIELD h="20" title="Fld4" w="150" x="290" y="30">fld4</TEXTFIELD>
			<TEXTFIELD h="20" title="Fld5" w="150" x="10" y="50">fld5</TEXTFIELD>
			<TEXTFIELD h="20" title="Fld6" w="150" x="290" y="50">fld6</TEXTFIELD>
			<TEXTFIELD h="20" title="Fld7" w="150" x="10" y="70">fld7</TEXTFIELD>
			<TEXTFIELD h="20" title="Fld8" w="150" x="290" y="70">fld8</TEXTFIELD>
			<TEXTFIELD h="20" title="Fld9" w="150" x="10" y="90">fld9</TEXTFIELD>
			<TEXTFIELD h="20" title="Fld10" w="150" x="290" y="90">fld10</TEXTFIELD>
			<TEXTFIELD h="20" title="Fld11" w="150" x="10" y="110">fld11</TEXTFIELD>
			<TEXTFIELD h="20" title="Fld12" w="150" x="290" y="110">fld12</TEXTFIELD>
			<TEXTFIELD h="20" title="Fld13" w="150" x="10" y="130">fld13</TEXTFIELD>
			<TEXTFIELD h="20" title="Fld14" w="150" x="290" y="130">fld14</TEXTFIELD>
			<TEXTFIELD h="20" title="Fld15" w="150" x="10" y="150">fld15</TEXTFIELD>
			<TEXTFIELD h="20" title="Fld16" w="150" x="290" y="150">fld16</TEXTFIELD>
			<TEXTFIELD h="20" title="Narrative" w="430" x="10" y="170">narrative</TEXTFIELD>
		</FORM>

	</DESK>

	<DESK h="500" key="30" name="Bot94" splitloc="250" splittype="vert" w="585">
		<GRID gridfilter="true" key="1" keyfield="fld0" name="Bot94" pos="top" table="bot94">
			<TEXTFIELD title="Fld0" w="40">fld0</TEXTFIELD>
			<TEXTFIELD title="Fld1" w="40">fld1</TEXTFIELD>
			<TEXTFIELD title="Fld2" w="40">fld2</TEXTFIELD>
			<TEXTFIELD title="Fld3" w="40">fld3</TEXTFIELD>
			<TEXTFIELD title="Fld4" w="40">fld4</TEXTFIELD>
			<TEXTFIELD title="Fld5" w="40">fld5</TEXTFIELD>
			<TEXTFIELD title="Fld6" w="40">fld6</TEXTFIELD>
			<TEXTFIELD title="Fld7" w="40">fld7</TEXTFIELD>
			<TEXTFIELD title="Fld8" w="40">fld8</TEXTFIELD>
			<TEXTFIELD title="Fld9" w="40">fld9</TEXTFIELD>
			<TEXTFIELD title="Fld10" w="40">fld10</TEXTFIELD>
			<TEXTFIELD title="Fld11" w="40">fld11</TEXTFIELD>
			<TEXTFIELD title="Fld12" w="40">fld12</TEXTFIELD>
			<TEXTFIELD title="Fld13" w="40">fld13</TEXTFIELD>
			<TEXTFIELD title="Fld14" w="40">fld14</TEXTFIELD>
			<TEXTFIELD title="Fld15" w="40">fld15</TEXTFIELD>
			<TEXTFIELD title="Narrative" w="40">narrative</TEXTFIELD>
		</GRID>

		<FORM autofield="fld0" key="2" linkfield="fld0" linkkey="1" name="Bot94" pos="bottom" table="bot94">
			<TEXTFIELD h="20" title="Fld1" w="150" x="10" y="10">fld1</TEXTFIELD>
			<TEXTFIELD h="20" title="Fld2" w="150" x="290" y="10">fld2</TEXTFIELD>
			<TEXTFIELD h="20" title="Fld3" w="150" x="10" y="30">fld3</TEXTFIELD>
			<TEXTFIELD h="20" title="Fld4" w="150" x="290" y="30">fld4</TEXTFIELD>
			<TEXTFIELD h="20" title="Fld5" w="150" x="10" y="50">fld5</TEXTFIELD>
			<TEXTFIELD h="20" title="Fld6" w="150" x="290" y="50">fld6</TEXTFIELD>
			<TEXTFIELD h="20" title="Fld7" w="150" x="10" y="70">fld7</TEXTFIELD>
			<TEXTFIELD h="20" title="Fld8" w="150" x="290" y="70">fld8</TEXTFIELD>
			<TEXTFIELD h="20" title="Fld9" w="150" x="10" y="90">fld9</TEXTFIELD>
			<TEXTFIELD h="20" title="Fld10" w="150" x="290" y="90">fld10</TEXTFIELD>
			<TEXTFIELD h="20" title="Fld11" w="150" x="10" y="110">fld11</TEXTFIELD>
			<TEXTFIELD h="20" title="Fld12" w="150" x="290" y="110">fld12</TEXTFIELD>
			<TEXTFIELD h="20" title="Fld13" w="150" x="10" y="130">fld13</TEXTFIELD>
			<TEXTFIELD h="20" title="Fld14" w="150" x="290" y="130">fld14</TEXTFIELD>
			<TEXTFIELD h="20" title="Fld15" w="150" x="10" y="150">fld15</TEXTFIELD>
			<TEXTFIELD h="20" title="Narrative" w="430" x="10" y="170">narrative</TEXTFIELD>
		</FORM>

	</DESK>

	<DESK h="500" key="31" name="Elements" splitloc="250" splittype="vert" w="585">
		<GRID gridfilter="true" key="1" keyfield="elementid" name="Elements" pos="top" table="elements">
			<TEXTFIELD title="Element" w="40">elementid</TEXTFIELD>
			<TEXTFIELD title="Code" w="40">code</TEXTFIELD>
			<TEXTFIELD title="El" w="40">el</TEXTFIELD>
			<TEXTFIELD title="Format" w="40">format</TEXTFIELD>
			<TEXTFIELD title="Description" w="40">description</TEXTFIELD>
			<TEXTFIELD title="Glossary" w="40">glossary</TEXTFIELD>
			<TEXTFIELD title="Status" w="40">status</TEXTFIELD>
			<TEXTFIELD title="Element" w="40">element</TEXTFIELD>
			<TEXTFIELD title="Pos" w="40">pos</TEXTFIELD>
			<TEXTFIELD title="Field Name" w="40">fieldname</TEXTFIELD>
		</GRID>

		<FORM autofield="elementid" key="2" linkfield="elementid" linkkey="1" name="Elements" pos="bottom" table="elements">
			<TEXTFIELD h="20" title="Code" w="150" x="10" y="10">code</TEXTFIELD>
			<TEXTFIELD h="20" title="El" w="150" x="290" y="10">el</TEXTFIELD>
			<TEXTFIELD h="20" title="Format" w="150" x="10" y="30">format</TEXTFIELD>
			<TEXTFIELD h="20" title="Description" w="150" x="290" y="30">description</TEXTFIELD>
			<TEXTFIELD h="20" title="Glossary" w="150" x="10" y="50">glossary</TEXTFIELD>
			<TEXTFIELD h="20" title="Status" w="150" x="290" y="50">status</TEXTFIELD>
			<TEXTFIELD h="20" title="Element" w="150" x="10" y="70">element</TEXTFIELD>
			<TEXTFIELD h="20" title="Pos" w="150" x="290" y="70">pos</TEXTFIELD>
			<TEXTFIELD h="20" title="Field Name" w="150" x="10" y="90">fieldname</TEXTFIELD>
		</FORM>

	</DESK>

	<DESK h="500" key="32" name="Headers" splitloc="250" splittype="vert" w="585">
		<GRID gridfilter="true" key="1" keyfield="headerid" name="Headers" pos="top" table="headers">
			<TEXTFIELD title="Header" w="40">headerid</TEXTFIELD>
			<TEXTFIELD title="Type" w="40">type</TEXTFIELD>
			<TEXTFIELD title="Code" w="40">code</TEXTFIELD>
			<TEXTFIELD title="Status" w="40">status</TEXTFIELD>
			<TEXTFIELD title="Format" w="40">format</TEXTFIELD>
			<TEXTFIELD title="Description" w="40">description</TEXTFIELD>
			<TEXTFIELD title="Link_tail" w="40">link_tail</TEXTFIELD>
			<TEXTFIELD title="Rec_table" w="40">rec_table</TEXTFIELD>
		</GRID>

		<FORM autofield="headerid" key="2" linkfield="headerid" linkkey="1" name="Headers" pos="bottom" table="headers">
			<TEXTFIELD h="20" title="Type" w="150" x="10" y="10">type</TEXTFIELD>
			<TEXTFIELD h="20" title="Code" w="150" x="290" y="10">code</TEXTFIELD>
			<TEXTFIELD h="20" title="Status" w="150" x="10" y="30">status</TEXTFIELD>
			<TEXTFIELD h="20" title="Format" w="150" x="290" y="30">format</TEXTFIELD>
			<TEXTFIELD h="20" title="Description" w="430" x="10" y="50">description</TEXTFIELD>
			<TEXTFIELD h="20" title="Link_tail" w="150" x="10" y="70">link_tail</TEXTFIELD>
			<TEXTFIELD h="20" title="Rec_table" w="150" x="290" y="70">rec_table</TEXTFIELD>
		</FORM>

	</DESK>

	<DESK h="500" key="101" name="Bar64" splitloc="0" splittype="horl" w="700">
		<REPORT jasperfile="bar64.jasper" name="Bar64" pos="bottom"></REPORT>
	</DESK>

	<DESK h="500" key="102" name="Bar65" splitloc="0" splittype="horl" w="700">
		<REPORT jasperfile="bar65.jasper" name="Bar65" pos="bottom"></REPORT>
	</DESK>

	<DESK h="500" key="103" name="Bar66" splitloc="0" splittype="horl" w="700">
		<REPORT jasperfile="bar66.jasper" name="Bar66" pos="bottom"></REPORT>
	</DESK>

	<DESK h="500" key="104" name="Bch02" splitloc="0" splittype="horl" w="700">
		<REPORT jasperfile="bch02.jasper" name="Bch02" pos="bottom"></REPORT>
	</DESK>

	<DESK h="500" key="105" name="Bct95" splitloc="0" splittype="horl" w="700">
		<REPORT jasperfile="bct95.jasper" name="Bct95" pos="bottom"></REPORT>
	</DESK>

	<DESK h="500" key="106" name="Bfh01" splitloc="0" splittype="horl" w="700">
		<REPORT jasperfile="bfh01.jasper" name="Bfh01" pos="bottom"></REPORT>
	</DESK>

	<DESK h="500" key="107" name="Bft99" splitloc="0" splittype="horl" w="700">
		<REPORT jasperfile="bft99.jasper" name="Bft99" pos="bottom"></REPORT>
	</DESK>

	<DESK h="500" key="108" name="Bkf81" splitloc="0" splittype="horl" w="700">
		<REPORT jasperfile="bkf81.jasper" name="Bkf81" pos="bottom"></REPORT>
	</DESK>

	<DESK h="500" key="109" name="Bki63" splitloc="0" splittype="horl" w="700">
		<REPORT jasperfile="bki63.jasper" name="Bki63" pos="bottom"></REPORT>
	</DESK>

	<DESK h="500" key="110" name="Bkp83" splitloc="0" splittype="horl" w="700">
		<REPORT jasperfile="bkp83.jasper" name="Bkp83" pos="bottom"></REPORT>
	</DESK>

	<DESK h="500" key="111" name="Bkp84" splitloc="0" splittype="horl" w="700">
		<REPORT jasperfile="bkp84.jasper" name="Bkp84" pos="bottom"></REPORT>
	</DESK>

	<DESK h="500" key="112" name="Bks24" splitloc="0" splittype="horl" w="700">
		<REPORT jasperfile="bks24.jasper" name="Bks24" pos="bottom"></REPORT>
	</DESK>

	<DESK h="500" key="113" name="Bks30" splitloc="0" splittype="horl" w="700">
		<REPORT jasperfile="bks30.jasper" name="Bks30" pos="bottom"></REPORT>
	</DESK>

	<DESK h="500" key="114" name="Bks39" splitloc="0" splittype="horl" w="700">
		<REPORT jasperfile="bks39.jasper" name="Bks39" pos="bottom"></REPORT>
	</DESK>

	<DESK h="500" key="115" name="Bks42" splitloc="0" splittype="horl" w="700">
		<REPORT jasperfile="bks42.jasper" name="Bks42" pos="bottom"></REPORT>
	</DESK>

	<DESK h="500" key="116" name="Bks45" splitloc="0" splittype="horl" w="700">
		<REPORT jasperfile="bks45.jasper" name="Bks45" pos="bottom"></REPORT>
	</DESK>

	<DESK h="500" key="117" name="Bks46" splitloc="0" splittype="horl" w="700">
		<REPORT jasperfile="bks46.jasper" name="Bks46" pos="bottom"></REPORT>
	</DESK>

	<DESK h="500" key="118" name="Bkt06" splitloc="0" splittype="horl" w="700">
		<REPORT jasperfile="bkt06.jasper" name="Bkt06" pos="bottom"></REPORT>
	</DESK>

	<DESK h="500" key="119" name="Bmd75" splitloc="0" splittype="horl" w="700">
		<REPORT jasperfile="bmd75.jasper" name="Bmd75" pos="bottom"></REPORT>
	</DESK>

	<DESK h="500" key="120" name="Bmd76" splitloc="0" splittype="horl" w="700">
		<REPORT jasperfile="bmd76.jasper" name="Bmd76" pos="bottom"></REPORT>
	</DESK>

	<DESK h="500" key="121" name="Bmp70" splitloc="0" splittype="horl" w="700">
		<REPORT jasperfile="bmp70.jasper" name="Bmp70" pos="bottom"></REPORT>
	</DESK>

	<DESK h="500" key="122" name="Bmp71" splitloc="0" splittype="horl" w="700">
		<REPORT jasperfile="bmp71.jasper" name="Bmp71" pos="bottom"></REPORT>
	</DESK>

	<DESK h="500" key="123" name="Bmp72" splitloc="0" splittype="horl" w="700">
		<REPORT jasperfile="bmp72.jasper" name="Bmp72" pos="bottom"></REPORT>
	</DESK>

	<DESK h="500" key="124" name="Bmp73" splitloc="0" splittype="horl" w="700">
		<REPORT jasperfile="bmp73.jasper" name="Bmp73" pos="bottom"></REPORT>
	</DESK>

	<DESK h="500" key="125" name="Bmp74" splitloc="0" splittype="horl" w="700">
		<REPORT jasperfile="bmp74.jasper" name="Bmp74" pos="bottom"></REPORT>
	</DESK>

	<DESK h="500" key="126" name="Bmp77" splitloc="0" splittype="horl" w="700">
		<REPORT jasperfile="bmp77.jasper" name="Bmp77" pos="bottom"></REPORT>
	</DESK>

	<DESK h="500" key="127" name="Bmp78" splitloc="0" splittype="horl" w="700">
		<REPORT jasperfile="bmp78.jasper" name="Bmp78" pos="bottom"></REPORT>
	</DESK>

	<DESK h="500" key="128" name="Boh03" splitloc="0" splittype="horl" w="700">
		<REPORT jasperfile="boh03.jasper" name="Boh03" pos="bottom"></REPORT>
	</DESK>

	<DESK h="500" key="129" name="Bot93" splitloc="0" splittype="horl" w="700">
		<REPORT jasperfile="bot93.jasper" name="Bot93" pos="bottom"></REPORT>
	</DESK>

	<DESK h="500" key="130" name="Bot94" splitloc="0" splittype="horl" w="700">
		<REPORT jasperfile="bot94.jasper" name="Bot94" pos="bottom"></REPORT>
	</DESK>

	<DESK h="500" key="131" name="Elements" splitloc="0" splittype="horl" w="700">
		<REPORT jasperfile="elements.jasper" name="Elements" pos="bottom"></REPORT>
	</DESK>

	<DESK h="500" key="132" name="Headers" splitloc="0" splittype="horl" w="700">
		<REPORT jasperfile="headers.jasper" name="Headers" pos="bottom"></REPORT>
	</DESK>

</APP>

